Workbook

Sheet Общее описание
A11: ЧТО НУЖНО, ЧТОБЫ ЗАПУСТИТЬ ПРИЛОЖЕНИЕ В КОНТЕЙНЕРЕ?

Sheet Контроли

Sheet Результаты
B2: Домен | C2: Процент выполнения всех практик кажого домена JCSF | D2: Процент выполнения каждого уровня зрелости JCSF
D3: 1 | E3: 2 | F3: 3 | G3: 4
B4: Общие контроли (gen) | C4: =(Практики!J14/Практики!H14)*100 -> 0 | D4: =Практики!E3 -> 0 | E4: =Практики!E7 -> 0 | F4: =Практики!E11 -> 0 | G4: =Практики!E13 -> 0
B5: Безопасность узлов сред контейнеризации (nodes) | C5: =(Практики!J47/Практики!H47)*100 -> 0 | D5: =Практики!E16 -> 0 | E5: =Практики!E23 -> 0 | F5: =Практики!E36 -> 0 | G5: =Практики!E43 -> 0
B6: Безопасность оркестратора Kubernetes (orchr) | C6: =(Практики!J83/Практики!H83)*100 -> 0 | D6: =Практики!E49 -> 0 | E6: =Практики!E60 -> 0 | F6: =Практики!E73 -> 0 | G6: =Практики!E80 -> 0
B7: Безопасность манифестов (man) | C7: =(Практики!J158/Практики!H158)*100 -> 0 | D7: =Практики!E140 -> 0 | E7: =Практики!E144 -> 0 | F7: =Практики!E152 -> 0 | G7: =Практики!E156 -> 0
B8: Безопасность сред контейнеризации Docker | C8: =(Практики!J122/Практики!H122)*100 -> 0 | D8: =Практики!E85 -> 0 | E8: =Практики!E92 -> 0 | F8: =Практики!E106 -> 0 | G8: =Практики!E115 -> 0
B9: Безопасность образов контейнеров (img) | C9: =(Практики!J138/Практики!H138)*100 -> 0 | D9: =Практики!E124 -> 0 | E9: =Практики!E129 -> 0 | F9: =Практики!E132 -> 0 | G9: =Практики!E136 -> 0
B10: Безопасность запущенных контейнеров (containers) | C10: =(Практики!J172/Практики!H172)*100 -> 0 | D10: =Практики!E160 -> 0 | E10: =Практики!E162 -> 0 | F10: =Практики!E165 -> 0 | G10: =Практики!E171 -> 0
B13: Домен | C13: Соответствие уровню зрелости каждого домена JCSF | D13: Общий уровень зрелости по JCSF
B14: Общие контроли (gen) | C14: =(Практики!J14/Практики!H14)*4 -> 0 | D14: =AVERAGE(C14:C20) -> 0
B15: Безопасность узлов сред контейнеризации (nodes) | C15: =(Практики!J47/Практики!H47)*4 -> 0
B16: Безопасность оркестратора Kubernetes (orchr) | C16: =(Практики!J83/Практики!H83)*4 -> 0
B17: Безопасность манифестов (man) | C17: =(Практики!J158/Практики!H158)*4 -> 0
B18: Безопасность сред контейнеризации Docker | C18: =(Практики!J122/Практики!H122)*4 -> 0
B19: Безопасность образов контейнеров (img) | C19: =(Практики!J138/Практики!H138)*4 -> 0
B20: Безопасность запущенных контейнеров (containers) | C20: =(Практики!J172/Практики!H172)*4 -> 0

Sheet Практики
A1: ID практики | B1: Требование | C1: Уровень зрелости | D1: Статус | E1: Соответствие уровню зрелости | F1: Классификация | G1: Уровень критичности | H1: Вес критерия | I1: Выполняется | J1: Итоговый балл | K1: CIS Kubernetes | L1: CIS Docker | M1: CIS Linux (Debian) | N1: CIS Linux (RHEL) | O1: 118 Приказ | P1: УБИ ФСТЭК | Q1: Примечание
A2: Общие практики безопасности (Generic)
A3: Gen-1-1 | B3: Создаются резервные копии критичных серверов, процесс резервирования является системным. | C3: 1 | D3: Не заполнено | E3: =(COUNTIF(D3:D6,$D$180)+(COUNTIF(D3:D6,$D$183)*0.5))/(COUNTA(D3:D6)-COUNTIF(D3:D6,$D$182)) -> 0 | F3: Резервное копирование | G3: Высокий | H3: =IF(D3="Не применимо",0,IF(G3="высокий",5,IF(G3="средний",3,IF(G3="низкий",1,"")))) -> 5 | I3: =IF(D3="Не применимо",0,IF(D3="Выполняется",1,IF(D3="Частично выполняется",0.5,IF(D3="Не выполняется",0,IF(D3="Не заполнено",0,""))))) -> 0 | J3: =I3*H3 -> 0 | K3: - | L3: - | M3: - | N3: -
A4: Gen-1-2 | B4: Должна быть обеспечена отказоустойчивость серверной инфраструктуры в рамках 1 сайта | C4: 1 | D4: Не заполнено | F4: Отказоустойчивость | G4: Высокий | H4: =IF(D4="Не применимо",0,IF(G4="высокий",5,IF(G4="средний",3,IF(G4="низкий",1,"")))) -> 5 | I4: =IF(D4="Не применимо",0,IF(D4="Выполняется",1,IF(D4="Частично выполняется",0.5,IF(D4="Не выполняется",0,IF(D4="Не заполнено",0,""))))) -> 0 | J4: =I4*H4 -> 0 | K4: - | L4: - | M4: - | N4: -
A5: Gen-1-3 | B5: Выполняется контроль сетевого трафика на уровне межсетевых экранов (L3/L4) в PROD сегменте (доступ к узлам) | C5: 1 | D5: Не заполнено | F5: Сетевая безопасность | G5: Высокий | H5: =IF(D5="Не применимо",0,IF(G5="высокий",5,IF(G5="средний",3,IF(G5="низкий",1,"")))) -> 5 | I5: =IF(D5="Не применимо",0,IF(D5="Выполняется",1,IF(D5="Частично выполняется",0.5,IF(D5="Не выполняется",0,IF(D5="Не заполнено",0,""))))) -> 0 | J5: =I5*H5 -> 0 | K5: - | L5: - | M5: - | N5: -
A6: Gen-1-4 | B6: PROD инфраструктура находится в выделенном сетевом сегменте | C6: 1 | D6: Не заполнено | F6: Сетевая безопасность | G6: Высокий | H6: =IF(D6="Не применимо",0,IF(G6="высокий",5,IF(G6="средний",3,IF(G6="низкий",1,"")))) -> 5 | I6: =IF(D6="Не применимо",0,IF(D6="Выполняется",1,IF(D6="Частично выполняется",0.5,IF(D6="Не выполняется",0,IF(D6="Не заполнено",0,""))))) -> 0 | J6: =I6*H6 -> 0 | K6: - | L6: - | M6: - | N6: -
A7: Gen-2-1 | B7: Удаленный доступ подрядчиков регламентирован, права минимально необходимы и контролируется. | C7: 2 | D7: Не заполнено | E7: =(COUNTIF(D7:D10,$D$180)+(COUNTIF(D7:D10,$D$183)*0.5))/(COUNTA(D7:D10)-COUNTIF(D7:D10,$D$182)) -> 0 | F7: Ролевая модель и разделение зон ответственности | G7: Высокий | H7: =IF(D7="Не применимо",0,IF(G7="высокий",5,IF(G7="средний",3,IF(G7="низкий",1,"")))) -> 5 | I7: =IF(D7="Не применимо",0,IF(D7="Выполняется",1,IF(D7="Частично выполняется",0.5,IF(D7="Не выполняется",0,IF(D7="Не заполнено",0,""))))) -> 0 | J7: =I7*H7 -> 0 | K7: - | L7: - | M7: - | N7: -
A8: Gen-2-2 | B8: Зоны распределения ответственности администраторов разграничены и задокументированы для оркестратора и ОС | C8: 2 | D8: Не заполнено | F8: Ролевая модель и разделение зон ответственности | G8: Средний | H8: =IF(D8="Не применимо",0,IF(G8="высокий",5,IF(G8="средний",3,IF(G8="низкий",1,"")))) -> 3 | I8: =IF(D8="Не применимо",0,IF(D8="Выполняется",1,IF(D8="Частично выполняется",0.5,IF(D8="Не выполняется",0,IF(D8="Не заполнено",0,""))))) -> 0 | J8: =I8*H8 -> 0 | K8: - | L8: - | M8: - | N8: -
A9: Gen-2-3 | B9: Процесс резервного копирования регламентирован | C9: 2 | D9: Не заполнено | F9: Резервное копирование | G9: Средний | H9: =IF(D9="Не применимо",0,IF(G9="высокий",5,IF(G9="средний",3,IF(G9="низкий",1,"")))) -> 3 | I9: =IF(D9="Не применимо",0,IF(D9="Выполняется",1,IF(D9="Частично выполняется",0.5,IF(D9="Не выполняется",0,IF(D9="Не заполнено",0,""))))) -> 0 | J9: =I9*H9 -> 0 | K9: - | L9: - | M9: - | N9: -
A10: Gen-2-4 | B10: Процесс восстановления доступности регламентирован | C10: 2 | D10: Не заполнено | F10: Резервное копирование | G10: Средний | H10: =IF(D10="Не применимо",0,IF(G10="высокий",5,IF(G10="средний",3,IF(G10="низкий",1,"")))) -> 3 | I10: =IF(D10="Не применимо",0,IF(D10="Выполняется",1,IF(D10="Частично выполняется",0.5,IF(D10="Не выполняется",0,IF(D10="Не заполнено",0,""))))) -> 0 | J10: =I10*H10 -> 0 | K10: - | L10: - | M10: - | N10: -
A11: Gen-3-1 | B11: Тестовая среда располагается в отдельном сетевом сегменте. Доступ к среде ограничен | C11: 3 | D11: Не заполнено | E11: =(COUNTIF(D11:D12,$D$180)+(COUNTIF(D11:D12,$D$183)*0.5))/(COUNTA(D11:D12)-COUNTIF(D11:D12,$D$182)) -> 0 | F11: Сетевая безопасность | G11: Средний | H11: =IF(D11="Не применимо",0,IF(G11="высокий",5,IF(G11="средний",3,IF(G11="низкий",1,"")))) -> 3 | I11: =IF(D11="Не применимо",0,IF(D11="Выполняется",1,IF(D11="Частично выполняется",0.5,IF(D11="Не выполняется",0,IF(D11="Не заполнено",0,""))))) -> 0 | J11: =I11*H11 -> 0 | K11: - | L11: - | M11: - | N11: -
A12: Gen-3-2 | B12: Проводятся учения по отработке плана аварийного восстановления с фактическим прохождением этапов восстановления на условно аварийном сервере | C12: 3 | D12: Не заполнено | F12: Резервное копирование | G12: Высокий | H12: =IF(D12="Не применимо",0,IF(G12="высокий",5,IF(G12="средний",3,IF(G12="низкий",1,"")))) -> 5 | I12: =IF(D12="Не применимо",0,IF(D12="Выполняется",1,IF(D12="Частично выполняется",0.5,IF(D12="Не выполняется",0,IF(D12="Не заполнено",0,""))))) -> 0 | J12: =I12*H12 -> 0 | K12: - | L12: - | M12: - | N12: -
A13: Gen-4-1 | B13: Обеспечена отказоустойчивость серверной инфраструктуры в рамках нескольких сайтов | C13: 4 | D13: Не заполнено | E13: =(COUNTIF(D13,$D$180)+(COUNTIF(D13,$D$183)*0.5))/(COUNTA(D13)-COUNTIF(D13,$D$182)) -> 0 | F13: Отказоустойчивость | G13: Средний | H13: =IF(D13="Не применимо",0,IF(G13="высокий",5,IF(G13="средний",3,IF(G13="низкий",1,"")))) -> 3 | I13: =IF(D13="Не применимо",0,IF(D13="Выполняется",1,IF(D13="Частично выполняется",0.5,IF(D13="Не выполняется",0,IF(D13="Не заполнено",0,""))))) -> 0 | J13: =I13*H13 -> 0 | K13: - | L13: - | M13: - | N13: -
G14: Максимальный балл | H14: =SUM(H3:H13) -> 45 | I14: Итоговый общий балл | J14: =SUM(J3:J13) -> 0
A15: Безопасность УЗЛОВ сред контейнеризации (nodes)
A16: Nodes-1-1 | B16: УЗ администраторов ОС серверов должны содержать уникальный идентификатор, позволяющий связать администратора с их действиями в ОС | C16: 1 | D16: Не заполнено | E16: =(COUNTIF(D16:D22,$D$180)+(COUNTIF(D16:D22,$D$183)*0.5))/(COUNTA(D16:D22)-COUNTIF(D16:D22,$D$182)) -> 0 | F16: Учетные записи | G16: Высокий | H16: =IF(D16="Не применимо",0,IF(G16="высокий",5,IF(G16="средний",3,IF(G16="низкий",1,"")))) -> 5 | I16: =IF(D16="Не применимо",0,IF(D16="Выполняется",1,IF(D16="Частично выполняется",0.5,IF(D16="Не выполняется",0,IF(D16="Не заполнено",0,""))))) -> 0 | J16: =I16*H16 -> 0 | K16: - | L16: 1.2.1 | M16: 7.2.5, 7.2.7 | N16: 7.2.4, 7.2.6
A17: Nodes-1-2 | B17: УЗ root не должна использоваться для администрирования ОС | C17: 1 | D17: Не заполнено | F17: Учетные записи | G17: Средний | H17: =IF(D17="Не применимо",0,IF(G17="высокий",5,IF(G17="средний",3,IF(G17="низкий",1,"")))) -> 3 | I17: =IF(D17="Не применимо",0,IF(D17="Выполняется",1,IF(D17="Частично выполняется",0.5,IF(D17="Не выполняется",0,IF(D17="Не заполнено",0,""))))) -> 0 | J17: =I17*H17 -> 0 | K17: - | L17: 1.2.1 | M17: 5.1.21, 5.4.2.1, 5.4.2.7, 5.4.2.8 | N17: 5.1.20, 5.4.2.1, 5.4.2.7, 5.4.2.8
A18: Nodes-1-3 | B18: Используются версии ОС, поддерживаемые производителем. Для неподдерживаемых версий ОС имеется расширенная поддержка | C18: 1 | D18: Не заполнено | F18: Версии ПО | G18: Высокий | H18: =IF(D18="Не применимо",0,IF(G18="высокий",5,IF(G18="средний",3,IF(G18="низкий",1,"")))) -> 5 | I18: =IF(D18="Не применимо",0,IF(D18="Выполняется",1,IF(D18="Частично выполняется",0.5,IF(D18="Не выполняется",0,IF(D18="Не заполнено",0,""))))) -> 0 | J18: =I18*H18 -> 0 | K18: - | L18: 1.2.1 | M18: 1.2.2.1 | N18: 1.2.2.1
A19: Nodes-1-4 | B19: Осуществляется сбор логов о состоянии серверов (мониторинг ИТ) - собираются данные о состоянии сервера. | C19: 1 | D19: Не заполнено | F19: Мониторинг | G19: Высокий | H19: =IF(D19="Не применимо",0,IF(G19="высокий",5,IF(G19="средний",3,IF(G19="низкий",1,"")))) -> 5 | I19: =IF(D19="Не применимо",0,IF(D19="Выполняется",1,IF(D19="Частично выполняется",0.5,IF(D19="Не выполняется",0,IF(D19="Не заполнено",0,""))))) -> 0 | J19: =I19*H19 -> 0 | K19: - | L19: - | M19: - | N19: -
A20: Nodes-1-5 | B20: Используется антивирусное ПО с постоянно обновляемыми базами. | C20: 1 | D20: Не заполнено | F20: СЗИ | G20: Средний | H20: =IF(D20="Не применимо",0,IF(G20="высокий",5,IF(G20="средний",3,IF(G20="низкий",1,"")))) -> 3 | I20: =IF(D20="Не применимо",0,IF(D20="Выполняется",1,IF(D20="Частично выполняется",0.5,IF(D20="Не выполняется",0,IF(D20="Не заполнено",0,""))))) -> 0 | J20: =I20*H20 -> 0 | K20: - | L20: - | M20: 1.2.2.1 | N20: 1.2.2.1
A21: Nodes-1-6 | B21: Реализованы механизмы синхронизации времени в ОС с целью возможности подтверждения времени записи событий | C21: 1 | D21: Не заполнено | F21: Харденинг | G21: Высокий | H21: =IF(D21="Не применимо",0,IF(G21="высокий",5,IF(G21="средний",3,IF(G21="низкий",1,"")))) -> 5 | I21: =IF(D21="Не применимо",0,IF(D21="Выполняется",1,IF(D21="Частично выполняется",0.5,IF(D21="Не выполняется",0,IF(D21="Не заполнено",0,""))))) -> 0 | J21: =I21*H21 -> 0 | K21: - | L21: 1.2.1 | M21: 2.3.1.1, 2.3.2.1, 2.3.2.2, 2.3.3.1, 2.3.3.2, 2.3.3.3 | N21: 2.3.1, 2.3.2, 2.3.3
A22: Nodes-1-7 | B22: Выполнены настройки сложности пароля: Возможность использования пустых паролей - нет длина пароля: 14; сложность: да; срок действия: не более года; блокирование известных паролей: 20 и более из ТОП, 5 ранее использованных; | C22: 1 | D22: Не заполнено | F22: Харденинг | G22: Высокий | H22: =IF(D22="Не применимо",0,IF(G22="высокий",5,IF(G22="средний",3,IF(G22="низкий",1,"")))) -> 5 | I22: =IF(D22="Не применимо",0,IF(D22="Выполняется",1,IF(D22="Частично выполняется",0.5,IF(D22="Не выполняется",0,IF(D22="Не заполнено",0,""))))) -> 0 | J22: =I22*H22 -> 0 | K22: - | L22: 1.2.1 | M22: 5.3.1.1, 5.3.1.2, 5.3.1.3, 5.3.2.1, 5.3.2.2, 5.3.2.3, 5.3.2.4, 5.3.3.1.1, 5.3.3.1.2, 5.3.3.1.3, 5.3.3.2.1, 5.3.3.2.2, 5.3.3.2.3, 5.3.3.2.4, 5.3.3.2.5, 5.3.3.2.6, 5.3.3.2.7, 5.3.3.2.8, 5.3.3.3.1, 5.3.3.3.2, 5.3.3.3.3, 5.4.1.1, 5.4.1.2, 5.4.1.3 | N22: 5.3.1.1, 5.3.1.2, 5.3.1.3, 5.3.1.4, 5.3.1.5, 5.3.2.1.1, 5.3.2.1.2, 5.3.2.1.3, 5.3.2.2.1, 5.3.2.2.2, 5.3.2.2.3, 5.3.2.2.4, 5.3.2.2.5, 5.3.2.2.6, 5.3.2.2.7, 5.3.2.3.1, 5.3.2.3.2, 5.3.2.3.3, 5.4.1.1, 5.4.1.2, 5.4.1.3
A23: Nodes-2-1 | B23: Привилегированные права в ОС имеют только УЗ, которым такой доступ необходим, данные УЗ актуальны | C23: 2 | D23: Не заполнено | E23: =(COUNTIF(D23:D35,$D$180)+(COUNTIF(D23:D35,$D$183)*0.5))/(COUNTA(D23:D35)-COUNTIF(D23:D35,$D$182)) -> 0 | F23: Учетные записи | G23: Высокий | H23: =IF(D23="Не применимо",0,IF(G23="высокий",5,IF(G23="средний",3,IF(G23="низкий",1,"")))) -> 5 | I23: =IF(D23="Не применимо",0,IF(D23="Выполняется",1,IF(D23="Частично выполняется",0.5,IF(D23="Не выполняется",0,IF(D23="Не заполнено",0,""))))) -> 0 | J23: =I23*H23 -> 0 | K23: - | L23: 1.2.1 | M23: 5.2.1, 5.2.2, 5.2.3, 5.2.4, 5.2.5, 5.2.6, 5.2.7 | N23: 5.2.1, 5.2.2, 5.2.3, 5.2.4, 5.2.5, 5.2.6, 5.2.7
A24: Nodes-2-2 | B24: Установлены актуальные обновления безопасности ОС, процесс обновления является системным | C24: 2 | D24: Не заполнено | F24: Версии ПО | G24: Высокий | H24: =IF(D24="Не применимо",0,IF(G24="высокий",5,IF(G24="средний",3,IF(G24="низкий",1,"")))) -> 5 | I24: =IF(D24="Не применимо",0,IF(D24="Выполняется",1,IF(D24="Частично выполняется",0.5,IF(D24="Не выполняется",0,IF(D24="Не заполнено",0,""))))) -> 0 | J24: =I24*H24 -> 0 | K24: - | L24: 1.2.1 | M24: 1.2.2.1 | N24: 1.2.2.1
A25: Nodes-2-3 | B25: Проводятся периодические сканирования ОС, направленные на выявление уязвимостей | C25: 2 | D25: Не заполнено | F25: Управление уязвимостями | G25: Высокий | H25: =IF(D25="Не применимо",0,IF(G25="высокий",5,IF(G25="средний",3,IF(G25="низкий",1,"")))) -> 5 | I25: =IF(D25="Не применимо",0,IF(D25="Выполняется",1,IF(D25="Частично выполняется",0.5,IF(D25="Не выполняется",0,IF(D25="Не заполнено",0,""))))) -> 0 | J25: =I25*H25 -> 0 | K25: - | L25: 1.2.1 | M25: - | N25: - | Q25: OpenVAS
A26: Nodes-2-4 | B26: Для установки ОС используется «золотой» образ | C26: 2 | D26: Не заполнено | F26: Золотой образ | G26: Высокий | H26: =IF(D26="Не применимо",0,IF(G26="высокий",5,IF(G26="средний",3,IF(G26="низкий",1,"")))) -> 5 | I26: =IF(D26="Не применимо",0,IF(D26="Выполняется",1,IF(D26="Частично выполняется",0.5,IF(D26="Не выполняется",0,IF(D26="Не заполнено",0,""))))) -> 0 | J26: =I26*H26 -> 0 | K26: - | L26: 1.2.1 | M26: - | N26: -
A27: Nodes-2-5 | B27: Обновления ОС для серверов, содержащих критичную информацию, устанавливаются только после предварительного успешного тестирования на специально выделенном стенде | C27: 2 | D27: Не заполнено | F27: Версии ПО | G27: Высокий | H27: =IF(D27="Не применимо",0,IF(G27="высокий",5,IF(G27="средний",3,IF(G27="низкий",1,"")))) -> 5 | I27: =IF(D27="Не применимо",0,IF(D27="Выполняется",1,IF(D27="Частично выполняется",0.5,IF(D27="Не выполняется",0,IF(D27="Не заполнено",0,""))))) -> 0 | J27: =I27*H27 -> 0 | K27: - | L27: 1.2.1 | M27: - | N27: -
A28: Nodes-2-6 | B28: Проводятся регулярные сканирования антивирусом | C28: 2 | D28: Не заполнено | F28: СЗИ | G28: Средний | H28: =IF(D28="Не применимо",0,IF(G28="высокий",5,IF(G28="средний",3,IF(G28="низкий",1,"")))) -> 3 | I28: =IF(D28="Не применимо",0,IF(D28="Выполняется",1,IF(D28="Частично выполняется",0.5,IF(D28="Не выполняется",0,IF(D28="Не заполнено",0,""))))) -> 0 | J28: =I28*H28 -> 0 | K28: - | L28: - | M28: 1.2.2.1 | N28: 1.2.2.1
A29: Nodes-2-7 | B29: Используются базовые настройки безопасности для ОС: - выполнен харденинг SSH: LoginGraceTime = 1 m; PermitRootLogin = no; MaxAuthTries = 6; IgnoreRhosts = yes; UsePAM = yes; TCPKeepAlive = yes; X11Forwarding = no; ClientAliveInterval = 600; ClientAliveCountMax = 3 | C29: 2 | D29: Не заполнено | F29: Харденинг | G29: Высокий | H29: =IF(D29="Не применимо",0,IF(G29="высокий",5,IF(G29="средний",3,IF(G29="низкий",1,"")))) -> 5 | I29: =IF(D29="Не применимо",0,IF(D29="Выполняется",1,IF(D29="Частично выполняется",0.5,IF(D29="Не выполняется",0,IF(D29="Не заполнено",0,""))))) -> 0 | J29: =I29*H29 -> 0 | K29: - | L29: 1.2.1 | M29: 5.1.7, 5.1.8, 5.1.11, 5.1.14, 5.1.17, 5.1.21, 5.1.23 | N29: 5.1.7, 5.1.8, 5.1.11, 5.1.13, 5.1.16, 5.1.20, 5.1.22
A30: Nodes-2-8 | B30: Логин на сервер только через SSH ключ | C30: 2 | D30: Не заполнено | F30: Харденинг | G30: Высокий | H30: =IF(D30="Не применимо",0,IF(G30="высокий",5,IF(G30="средний",3,IF(G30="низкий",1,"")))) -> 5 | I30: =IF(D30="Не применимо",0,IF(D30="Выполняется",1,IF(D30="Частично выполняется",0.5,IF(D30="Не выполняется",0,IF(D30="Не заполнено",0,""))))) -> 0 | J30: =I30*H30 -> 0 | K30: - | L30: 1.2.1 | M30: 5.1.2, 5.1.4, 5.1.20, 5.1.23 | N30: 5.1.2, 5.1.4, 5.1.19, 5.1.22
A31: Nodes-2-9 | B31: Определены и настроены критичные события, которые должны собираться с *nix-серверов (перечень параметров). События передаются и анализируются в SIEM | C31: 2 | D31: Не заполнено | F31: События ИБ | G31: Высокий | H31: =IF(D31="Не применимо",0,IF(G31="высокий",5,IF(G31="средний",3,IF(G31="низкий",1,"")))) -> 5 | I31: =IF(D31="Не применимо",0,IF(D31="Выполняется",1,IF(D31="Частично выполняется",0.5,IF(D31="Не выполняется",0,IF(D31="Не заполнено",0,""))))) -> 0 | J31: =I31*H31 -> 0 | K31: - | L31: - | M31: 6.1.1.1.1, 6.1.1.1.2, 6.1.1.1.3, 6.1.1.1.4, 6.1.1.1.5, 6.1.1.1.6, 6.1.1.2.1, 6.1.1.2.2, 6.1.1.2.3, 6.1.1.2.4, 6.1.2.1, 6.1.2.2, 6.1.2.3, 6.1.2.4, 6.1.2.5, 6.1.2.6, 6.1.2.7, 6.1.2.8, 6.1.2.9, 6.1.2.10, 6.1.2.11, 6.2.1.1, 6.2.1.2, 6.2.1.3, 6.2.1.4, 6.2.2.1, 6.2.2.2, 6.2.2.3, 6.2.2.4, 6.2.3.1, 6.2.3.2, 6.2.3.3, 6.2.3.4, 6.2.3.5, 6.2.3.6, 6.2.3.7, 6.2.3.8, 6.2.3.9, 6.2.3.10, 6.2.3.11, 6.2.3.12, 6.2.3.13, 6.2.3.14, 6.2.3.15, 6.2.3.16, 6.2.3.17, 6.2.3.18, 6.2.3.19, 6.2.3.20, 6.2.3.21, 6.2.3.22, 6.2.3.23, 6.2.3.24, 6.2.3.25, 6.2.3.26, 6.2.3.27, 6.2.3.28, 6.2.3.29, 6.2.3.30, 6.2.3.31, 6.2.3.32, 6.2.3.33, 6.2.3.33, 6.2.3.34, 6.2.3.35, 6.2.3.36, 6.2.3.37 | N31: 6.2.1.1, 6.2.1.2, 6.2.1.3, 6.2.1.4, 6.2.2.1.1, 6.2.2.1.2, 6.2.2.1.3, 6.2.2.1.4, 6.2.2.2, 6.2.2.3, 6.2.2.4, 6.2.3.1, 6.2.3.2, 6.2.3.3, 6.2.3.4, 6.2.3.5, 6.2.3.6, 6.2.3.7, 6.2.3.8, 6.3.1.1, 6.3.1.2, 6.3.1.3, 6.3.1.4, 6.3.2.1, 6.3.2.2, 6.3.2.3, 6.3.2.4, 6.3.3.1, 6.3.3.2, 6.3.3.3, 6.3.3.4, 6.3.3.5, 6.3.3.6, 6.3.3.7, 6.3.3.8, 6.3.3.9, 6.3.3.10, 6.3.3.11, 6.3.3.12, 6.3.3.13, 6.3.3.14, 6.3.3.15, 6.3.3.16, 6.3.3.17, 6.3.3.18, 6.3.3.19, 6.3.3.20, 6.3.3.21, 6.3.3.22, 6.3.3.23, 6.3.3.24, 6.3.3.25, 6.3.3.26, 6.3.3.27, 6.3.3.28, 6.3.3.29, 6.3.3.30, 6.3.3.31, 6.3.3.32, 6.3.3.33, 6.3.3.33, 6.3.3.34, 6.3.3.35, 6.3.3.36, 6.3.3.37 | O31: 13.1
A32: Nodes-2-10 | B32: Определен список возможных инцидентов ИБ в части ОС | C32: 2 | D32: Не заполнено | F32: События ИБ | G32: Высокий | H32: =IF(D32="Не применимо",0,IF(G32="высокий",5,IF(G32="средний",3,IF(G32="низкий",1,"")))) -> 5 | I32: =IF(D32="Не применимо",0,IF(D32="Выполняется",1,IF(D32="Частично выполняется",0.5,IF(D32="Не выполняется",0,IF(D32="Не заполнено",0,""))))) -> 0 | J32: =I32*H32 -> 0 | K32: - | L32: - | M32: - | N32: -
A33: Nodes-2-11 | B33: Выполняется ревизия УЗ администраторов ОС. В случае необходимости, УЗ деактивируется или отключается | C33: 2 | D33: Не заполнено | F33: Учетные записи | G33: Средний | H33: =IF(D33="Не применимо",0,IF(G33="высокий",5,IF(G33="средний",3,IF(G33="низкий",1,"")))) -> 3 | I33: =IF(D33="Не применимо",0,IF(D33="Выполняется",1,IF(D33="Частично выполняется",0.5,IF(D33="Не выполняется",0,IF(D33="Не заполнено",0,""))))) -> 0 | J33: =I33*H33 -> 0 | K33: - | L33: 1.2.1 | M33: - | N33: -
A34: Nodes-2-12 | B34: Неразрешенное ПО или не требуемое для администрирования на ОС хост-серверов не установлено | C34: 2 | D34: Не заполнено | F34: Харденинг | G34: Высокий | H34: =IF(D34="Не применимо",0,IF(G34="высокий",5,IF(G34="средний",3,IF(G34="низкий",1,"")))) -> 5 | I34: =IF(D34="Не применимо",0,IF(D34="Выполняется",1,IF(D34="Частично выполняется",0.5,IF(D34="Не выполняется",0,IF(D34="Не заполнено",0,""))))) -> 0 | J34: =I34*H34 -> 0 | K34: - | L34: 1.2.1 | M34: 2.1.1, 2.1.2, 2.1.3, 2.1.4, 2.1.5, 2.1.6, 2.1.7, 2.1.8, 2.1.9, 2.1.10, 2.1.11, 2.1.12, 2.1.13, 2.1.14, 2.1.15, 2.1.16, 2.1.17, 2.1.18, 2.1.19, 2.1.20, 2.1.21, 2.1.22, 2.1.23 | N34: 2.1.1, 2.1.2, 2.1.3, 2.1.4, 2.1.5, 2.1.6, 2.1.7, 2.1.8, 2.1.9, 2.1.10, 2.1.11, 2.1.12, 2.1.13, 2.1.14, 2.1.15, 2.1.16, 2.1.17, 2.1.18, 2.1.19, 2.1.20, 2.1.21, 2.1.22
A35: Nodes-2-13 | B35: Для размещения контейнеров на дисковой подсистеме используется отдельная партиция | C35: 2 | D35: Не заполнено | F35: Харденинг | G35: Средний | H35: =IF(D35="Не применимо",0,IF(G35="высокий",5,IF(G35="средний",3,IF(G35="низкий",1,"")))) -> 3 | I35: =IF(D35="Не применимо",0,IF(D35="Выполняется",1,IF(D35="Частично выполняется",0.5,IF(D35="Не выполняется",0,IF(D35="Не заполнено",0,""))))) -> 0 | J35: =I35*H35 -> 0 | K35: - | L35: 1.1.1 | M35: - | N35: -
A36: Nodes-3-1 | B36: Процесс установки обновлений безопасности ОС регламентирован | C36: 3 | D36: Не заполнено | E36: =(COUNTIF(D36:D42,$D$180)+(COUNTIF(D36:D42,$D$183)*0.5))/(COUNTA(D36:D42)-COUNTIF(D36:D42,$D$182)) -> 0 | F36: Версии ПО | G36: Средний | H36: =IF(D36="Не применимо",0,IF(G36="высокий",5,IF(G36="средний",3,IF(G36="низкий",1,"")))) -> 3 | I36: =IF(D36="Не применимо",0,IF(D36="Выполняется",1,IF(D36="Частично выполняется",0.5,IF(D36="Не выполняется",0,IF(D36="Не заполнено",0,""))))) -> 0 | J36: =I36*H36 -> 0 | K36: - | L36: 1.2.1 | M36: - | N36: -
A37: Nodes-3-2 | B37: Проводится сканирование «золотого» образа ОС на уязвимости | C37: 3 | D37: Не заполнено | F37: Золотой образ | G37: Высокий | H37: =IF(D37="Не применимо",0,IF(G37="высокий",5,IF(G37="средний",3,IF(G37="низкий",1,"")))) -> 5 | I37: =IF(D37="Не применимо",0,IF(D37="Выполняется",1,IF(D37="Частично выполняется",0.5,IF(D37="Не выполняется",0,IF(D37="Не заполнено",0,""))))) -> 0 | J37: =I37*H37 -> 0 | K37: - | L37: 1.2.1 | M37: - | N37: -
A38: Nodes-3-3 | B38: Процесс настройки параметров безопасности ОС регламентирован, используются стандарты безопасного конфигурирования c минимальным количеством параметров | C38: 3 | D38: Не заполнено | F38: Харденинг | G38: Средний | H38: =IF(D38="Не применимо",0,IF(G38="высокий",5,IF(G38="средний",3,IF(G38="низкий",1,"")))) -> 3 | I38: =IF(D38="Не применимо",0,IF(D38="Выполняется",1,IF(D38="Частично выполняется",0.5,IF(D38="Не выполняется",0,IF(D38="Не заполнено",0,""))))) -> 0 | J38: =I38*H38 -> 0 | K38: - | L38: 1.2.1 | M38: All | N38: All
A39: Nodes-3-4 | B39: Включен хостовый МЭ и настроен в соответствии с правилом «запрещено все, что не разрешено» | C39: 3 | D39: Не заполнено | F39: Харденинг | G39: Высокий | H39: =IF(D39="Не применимо",0,IF(G39="высокий",5,IF(G39="средний",3,IF(G39="низкий",1,"")))) -> 5 | I39: =IF(D39="Не применимо",0,IF(D39="Выполняется",1,IF(D39="Частично выполняется",0.5,IF(D39="Не выполняется",0,IF(D39="Не заполнено",0,""))))) -> 0 | J39: =I39*H39 -> 0 | K39: - | L39: 1.2.1 | M39: 4.1.1, 4.1.2, 4.1.3, 4.1.4, 4.1.5 | N39: 4.1.1, 4.1.2, 4.1.3, 4.1.4, 4.1.5, 4.1.6, 4.1.7
A40: Nodes-3-5 | B40: Определен перечень базовых СЗИ, устанавливаемых на серверы (помимо антивируса) | C40: 3 | D40: Не заполнено | F40: СЗИ | G40: Средний | H40: =IF(D40="Не применимо",0,IF(G40="высокий",5,IF(G40="средний",3,IF(G40="низкий",1,"")))) -> 3 | I40: =IF(D40="Не применимо",0,IF(D40="Выполняется",1,IF(D40="Частично выполняется",0.5,IF(D40="Не выполняется",0,IF(D40="Не заполнено",0,""))))) -> 0 | J40: =I40*H40 -> 0 | K40: - | L40: - | M40: 1.2.2.1 | N40: 1.2.2.1
A41: Nodes-3-6 | B41: Проводятся на регулярной основе внутренние аудиты ИБ конфигурационных настроек ОС | C41: 3 | D41: Не заполнено | F41: Харденинг | G41: Высокий | H41: =IF(D41="Не применимо",0,IF(G41="высокий",5,IF(G41="средний",3,IF(G41="низкий",1,"")))) -> 5 | I41: =IF(D41="Не применимо",0,IF(D41="Выполняется",1,IF(D41="Частично выполняется",0.5,IF(D41="Не выполняется",0,IF(D41="Не заполнено",0,""))))) -> 0 | J41: =I41*H41 -> 0 | K41: - | L41: 1.2.1 | M41: - | N41: -
A42: Nodes-3-7 | B42: Небезопасные службы ОС (стандартные службы, например, telnet и нестандартные службы - службы стороннего ПО для удаленного доступа и т.д.) отсутствуют или отключены | C42: 3 | D42: Не заполнено | F42: Харденинг | G42: Высокий | H42: =IF(D42="Не применимо",0,IF(G42="высокий",5,IF(G42="средний",3,IF(G42="низкий",1,"")))) -> 5 | I42: =IF(D42="Не применимо",0,IF(D42="Выполняется",1,IF(D42="Частично выполняется",0.5,IF(D42="Не выполняется",0,IF(D42="Не заполнено",0,""))))) -> 0 | J42: =I42*H42 -> 0 | K42: - | L42: 1.2.1 | M42: 2.2.1, 2.2.2, 2.2.3, 2.2.4, 2.2.5, 2.2.6 | N42: 2.2.1, 2.2.2, 2.2.3, 2.2.4
A43: Nodes-4-1 | B43: Применяется шифрование диска | C43: 4 | D43: Не заполнено | E43: =(COUNTIF(D43:D46,$D$180)+(COUNTIF(D43:D46,$D$183)*0.5))/(COUNTA(D43:D46)-COUNTIF(D43:D46,$D$182)) -> 0 | F43: Харденинг | G43: Низкий | H43: =IF(D43="Не применимо",0,IF(G43="высокий",5,IF(G43="средний",3,IF(G43="низкий",1,"")))) -> 1 | I43: =IF(D43="Не применимо",0,IF(D43="Выполняется",1,IF(D43="Частично выполняется",0.5,IF(D43="Не выполняется",0,IF(D43="Не заполнено",0,""))))) -> 0 | J43: =I43*H43 -> 0 | K43: - | L43: 1.2.1 | M43: - | N43: -
A44: Nodes-4-2 | B44: Должны использоваться специально настроенные АРМ (SAW/PAW – закрытая рабочая станция с высоким уровнем защиты) для администрирования инфраструктуры | C44: 4 | D44: Не заполнено | F44: СЗИ | G44: Средний | H44: =IF(D44="Не применимо",0,IF(G44="высокий",5,IF(G44="средний",3,IF(G44="низкий",1,"")))) -> 3 | I44: =IF(D44="Не применимо",0,IF(D44="Выполняется",1,IF(D44="Частично выполняется",0.5,IF(D44="Не выполняется",0,IF(D44="Не заполнено",0,""))))) -> 0 | J44: =I44*H44 -> 0 | K44: - | L44: - | M44: - | N44: -
A45: Nodes-4-3 | B45: Используются стандарты безопасности, включающие в себя большую часть настроек на основе CIS Benchmark | C45: 4 | D45: Не заполнено | F45: Харденинг | G45: Средний | H45: =IF(D45="Не применимо",0,IF(G45="высокий",5,IF(G45="средний",3,IF(G45="низкий",1,"")))) -> 3 | I45: =IF(D45="Не применимо",0,IF(D45="Выполняется",1,IF(D45="Частично выполняется",0.5,IF(D45="Не выполняется",0,IF(D45="Не заполнено",0,""))))) -> 0 | J45: =I45*H45 -> 0 | K45: - | L45: 1.2.1 | M45: All | N45: All
A46: Nodes-4-4 | B46: При хранении настроек и развертывании ОС используется подход IaC | C46: 4 | D46: Не заполнено | F46: IaC | G46: Средний | H46: =IF(D46="Не применимо",0,IF(G46="высокий",5,IF(G46="средний",3,IF(G46="низкий",1,"")))) -> 3 | I46: =IF(D46="Не применимо",0,IF(D46="Выполняется",1,IF(D46="Частично выполняется",0.5,IF(D46="Не выполняется",0,IF(D46="Не заполнено",0,""))))) -> 0 | J46: =I46*H46 -> 0 | K46: - | L46: - | M46: - | N46: -
G47: Максимальный балл | H47: =SUM(H16:H46) -> 129 | I47: Итоговый общий балл | J47: =SUM(J16:J46) -> 0
A48: Безопасность оркестратора (Orchestrator)
A49: Orch-1-1 | B49: Для доступа к kube-apiserver используется аутентификация и авторизация | C49: 1 | D49: Не заполнено | E49: =(COUNTIF(D49:D59,$D$180)+(COUNTIF(D49:D59,$D$183)*0.5))/(COUNTA(D49:D59)-COUNTIF(D49:D59,$D$182)) -> 0 | F49: Аутентификация и авторизация | G49: Высокий | H49: =IF(D49="Не применимо",0,IF(G49="высокий",5,IF(G49="средний",3,IF(G49="низкий",1,"")))) -> 5 | I49: =IF(D49="Не применимо",0,IF(D49="Выполняется",1,IF(D49="Частично выполняется",0.5,IF(D49="Не выполняется",0,IF(D49="Не заполнено",0,""))))) -> 0 | J49: =I49*H49 -> 0 | K49: 1.2.1; 1.2.6; 1.2.7; 1.2.8 | L49: - | M49: - | N49: - | O49: 15.1
A50: Orch-1-2 | B50: Для доступа к kube-apiserver не используется базовая аутентификация | C50: 1 | D50: Не заполнено | F50: Аутентификация и авторизация | G50: Высокий | H50: =IF(D50="Не применимо",0,IF(G50="высокий",5,IF(G50="средний",3,IF(G50="низкий",1,"")))) -> 5 | I50: =IF(D50="Не применимо",0,IF(D50="Выполняется",1,IF(D50="Частично выполняется",0.5,IF(D50="Не выполняется",0,IF(D50="Не заполнено",0,""))))) -> 0 | J50: =I50*H50 -> 0 | K50: 1.2.2 | L50: - | M50: - | N50: - | Q50: Deprecated с 1.16
A51: Orch-1-3 | B51: УЗ администраторов Kubernetes должны содержать уникальный идентификатор, позволяющий связать администратора с их действиями в среде контейнерной оркестрации | C51: 1 | D51: Не заполнено | F51: Учетные записи | G51: Высокий | H51: =IF(D51="Не применимо",0,IF(G51="высокий",5,IF(G51="средний",3,IF(G51="низкий",1,"")))) -> 5 | I51: =IF(D51="Не применимо",0,IF(D51="Выполняется",1,IF(D51="Частично выполняется",0.5,IF(D51="Не выполняется",0,IF(D51="Не заполнено",0,""))))) -> 0 | J51: =I51*H51 -> 0 | K51: 3.1.2; 3.1.3 | L51: - | M51: - | N51: -
A52: Orch-1-4 | B52: Для доступа к kube-apiserver используется только защищенное TLS соединение | C52: 1 | D52: Не заполнено | F52: Харденинг | G52: Высокий | H52: =IF(D52="Не применимо",0,IF(G52="высокий",5,IF(G52="средний",3,IF(G52="низкий",1,"")))) -> 5 | I52: =IF(D52="Не применимо",0,IF(D52="Выполняется",1,IF(D52="Частично выполняется",0.5,IF(D52="Не выполняется",0,IF(D52="Не заполнено",0,""))))) -> 0 | J52: =I52*H52 -> 0 | K52: 1.2.24; 1.2.29 | L52: - | M52: - | N52: -
A53: Orch-1-5 | B53: Для коммуникации между узлами кластера (master, worker, infrastructure) используются только шифрованные соединения TLS | C53: 1 | D53: Не заполнено | F53: Харденинг | G53: Высокий | H53: =IF(D53="Не применимо",0,IF(G53="высокий",5,IF(G53="средний",3,IF(G53="низкий",1,"")))) -> 5 | I53: =IF(D53="Не применимо",0,IF(D53="Выполняется",1,IF(D53="Частично выполняется",0.5,IF(D53="Не выполняется",0,IF(D53="Не заполнено",0,""))))) -> 0 | J53: =I53*H53 -> 0 | K53: 1.2.4; 1.2.5; 4.2.3 | L53: 7.3 | M53: - | N53: -
A54: Orch-1-6 | B54: Admission controller AlwaysAdmit не используется | C54: 1 | D54: Не заполнено | F54: Харденинг | G54: Высокий | H54: =IF(D54="Не применимо",0,IF(G54="высокий",5,IF(G54="средний",3,IF(G54="низкий",1,"")))) -> 5 | I54: =IF(D54="Не применимо",0,IF(D54="Выполняется",1,IF(D54="Частично выполняется",0.5,IF(D54="Не выполняется",0,IF(D54="Не заполнено",0,""))))) -> 0 | J54: =I54*H54 -> 0 | K54: 1.2.10 | L54: - | M54: - | N54: - | Q54: Deprecated с 1.13
A55: Orch-1-7 | B55: Для доступа kube-apiserver к etcd используется аутентификация через сертификаты | C55: 1 | D55: Не заполнено | F55: Харденинг | G55: Высокий | H55: =IF(D55="Не применимо",0,IF(G55="высокий",5,IF(G55="средний",3,IF(G55="низкий",1,"")))) -> 5 | I55: =IF(D55="Не применимо",0,IF(D55="Выполняется",1,IF(D55="Частично выполняется",0.5,IF(D55="Не выполняется",0,IF(D55="Не заполнено",0,""))))) -> 0 | J55: =I55*H55 -> 0 | K55: 1.2.23; 1.2.26 | L55: - | M55: - | N55: -
A56: Orch-1-8 | B56: Анонимная аутентификация kubelet отключена | C56: 1 | D56: Не заполнено | F56: Харденинг | G56: Высокий | H56: =IF(D56="Не применимо",0,IF(G56="высокий",5,IF(G56="средний",3,IF(G56="низкий",1,"")))) -> 5 | I56: =IF(D56="Не применимо",0,IF(D56="Выполняется",1,IF(D56="Частично выполняется",0.5,IF(D56="Не выполняется",0,IF(D56="Не заполнено",0,""))))) -> 0 | J56: =I56*H56 -> 0 | K56: 4.2.1; 4.2.2 | L56: - | M56: - | N56: -
A57: Orch-1-9 | B57: Read-only доступ к kubelet не используется | C57: 1 | D57: Не заполнено | F57: Харденинг | G57: Высокий | H57: =IF(D57="Не применимо",0,IF(G57="высокий",5,IF(G57="средний",3,IF(G57="низкий",1,"")))) -> 5 | I57: =IF(D57="Не применимо",0,IF(D57="Выполняется",1,IF(D57="Частично выполняется",0.5,IF(D57="Не выполняется",0,IF(D57="Не заполнено",0,""))))) -> 0 | J57: =I57*H57 -> 0 | K57: 4.2.4 | L57: - | M57: - | N57: -
A58: Orch-1-10 | B58: Для доступа к kubelet используется только шифрованный трафик TLS | C58: 1 | D58: Не заполнено | F58: Харденинг | G58: Высокий | H58: =IF(D58="Не применимо",0,IF(G58="высокий",5,IF(G58="средний",3,IF(G58="низкий",1,"")))) -> 5 | I58: =IF(D58="Не применимо",0,IF(D58="Выполняется",1,IF(D58="Частично выполняется",0.5,IF(D58="Не выполняется",0,IF(D58="Не заполнено",0,""))))) -> 0 | J58: =I58*H58 -> 0 | K58: 4.2.3; 4.2.9; 4.2.12 | L58: - | M58: - | N58: -
A59: Orch-1-11 | B59: Используется webhook авторизация kubelet с использованием сертификата kube-apiserver | C59: 1 | D59: Не заполнено | F59: Харденинг | G59: Средний | H59: =IF(D59="Не применимо",0,IF(G59="высокий",5,IF(G59="средний",3,IF(G59="низкий",1,"")))) -> 3 | I59: =IF(D59="Не применимо",0,IF(D59="Выполняется",1,IF(D59="Частично выполняется",0.5,IF(D59="Не выполняется",0,IF(D59="Не заполнено",0,""))))) -> 0 | J59: =I59*H59 -> 0 | K59: 4.2.2 | L59: - | M59: - | N59: -
A60: Orch-2-1 | B60: УЗ администраторов оркестратора подвергаются ревизии. В случае необходимости, УЗ деактивируются или отключаются | C60: 2 | D60: Не заполнено | E60: =(COUNTIF(D60:D72,$D$180)+(COUNTIF(D60:D72,$D$183)*0.5))/(COUNTA(D60:D72)-COUNTIF(D60:D72,$D$182)) -> 0 | F60: Учетные записи | G60: Высокий | H60: =IF(D60="Не применимо",0,IF(G60="высокий",5,IF(G60="средний",3,IF(G60="низкий",1,"")))) -> 5 | I60: =IF(D60="Не применимо",0,IF(D60="Выполняется",1,IF(D60="Частично выполняется",0.5,IF(D60="Не выполняется",0,IF(D60="Не заполнено",0,""))))) -> 0 | J60: =I60*H60 -> 0 | K60: 5.1.1 | L60: - | M60: - | N60: -
A61: Orch-2-2 | B61: Установлены актуальные обновления безопасности оркестратора, процесс обновления является системным | C61: 2 | D61: Не заполнено | F61: Версии ПО | G61: Высокий | H61: =IF(D61="Не применимо",0,IF(G61="высокий",5,IF(G61="средний",3,IF(G61="низкий",1,"")))) -> 5 | I61: =IF(D61="Не применимо",0,IF(D61="Выполняется",1,IF(D61="Частично выполняется",0.5,IF(D61="Не выполняется",0,IF(D61="Не заполнено",0,""))))) -> 0 | J61: =I61*H61 -> 0 | K61: - | L61: 1.2.2 | M61: - | N61: -
A62: Orch-2-3 | B62: УЗ cluster-admin не используется для администрирования кластеров Kubernetes | C62: 2 | D62: Не заполнено | F62: Учетные записи | G62: Средний | H62: =IF(D62="Не применимо",0,IF(G62="высокий",5,IF(G62="средний",3,IF(G62="низкий",1,"")))) -> 3 | I62: =IF(D62="Не применимо",0,IF(D62="Выполняется",1,IF(D62="Частично выполняется",0.5,IF(D62="Не выполняется",0,IF(D62="Не заполнено",0,""))))) -> 0 | J62: =I62*H62 -> 0 | K62: 5.1.1 | L62: - | M62: - | N62: -
A63: Orch-2-4 | B63: Admission controller AlwaysPullImages активирован и используется | C63: 2 | D63: Не заполнено | F63: Харденинг | G63: Низкий | H63: =IF(D63="Не применимо",0,IF(G63="высокий",5,IF(G63="средний",3,IF(G63="низкий",1,"")))) -> 1 | I63: =IF(D63="Не применимо",0,IF(D63="Выполняется",1,IF(D63="Частично выполняется",0.5,IF(D63="Не выполняется",0,IF(D63="Не заполнено",0,""))))) -> 0 | J63: =I63*H63 -> 0 | K63: 1.2.11 | L63: - | M63: - | N63: -
A64: Orch-2-5 | B64: Разрешения на конфигурационные файлы, хранящиеся на узлах master соответствуют лучшим практикам CIS | C64: 2 | D64: Не заполнено | F64: Харденинг | G64: Средний | H64: =IF(D64="Не применимо",0,IF(G64="высокий",5,IF(G64="средний",3,IF(G64="низкий",1,"")))) -> 3 | I64: =IF(D64="Не применимо",0,IF(D64="Выполняется",1,IF(D64="Частично выполняется",0.5,IF(D64="Не выполняется",0,IF(D64="Не заполнено",0,""))))) -> 0 | J64: =I64*H64 -> 0 | K64: 1.1.1; 1.1.2; 1.1.3; 1.1.4; 1.1.5; 1.1.6; 1.1.7; 1.1.8; 1.1.9; 1.1.10; 1.1.11; 1.1.12; 1.1.13; 1.1.14; 1.1.15; 1.1.16; 1.1.17; 1.1.18; 1.1.19; 1.1.20; 1.1.21 | L64: 3.1; 3.2; 3.3; 3.4; 3.5; 3.6; 3.7; 3.8; 3.9; 3.10; 3.11; 3.12; 3.13; 3.14; 3.15; 3.16; 3.17; 3.18; 3.19; 3.20; 3.21; 3.22; 3.23; 3.24 | M64: - | N64: - | Q64: kube-bench
A65: Orch-2-6 | B65: Разрешения на конфигурационные файлы, хранящиеся на узлах worker соответствуют лучшим практикам CIS | C65: 2 | D65: Не заполнено | F65: Харденинг | G65: Средний | H65: =IF(D65="Не применимо",0,IF(G65="высокий",5,IF(G65="средний",3,IF(G65="низкий",1,"")))) -> 3 | I65: =IF(D65="Не применимо",0,IF(D65="Выполняется",1,IF(D65="Частично выполняется",0.5,IF(D65="Не выполняется",0,IF(D65="Не заполнено",0,""))))) -> 0 | J65: =I65*H65 -> 0 | K65: 4.1.1; 4.1.2; 4.1.3; 4.1.4; 4.1.5; 4.1.6; 4.1.7; 4.1.8; 4.1.9; 4.1.10 | L65: 3.1; 3.2; 3.3; 3.4; 3.5; 3.6; 3.7; 3.8; 3.9; 3.10; 3.11; 3.12; 3.13; 3.14; 3.15; 3.16; 3.17; 3.18; 3.19; 3.20; 3.21; 3.22; 3.23; 3.24 | M65: - | N65: - | Q65: kube-bench
A66: Orch-2-7 | B66: Используются версии оркестратора, поддерживаемые производителем. Для неподдерживаемых версий ОС имеется расширенная поддержка | C66: 2 | D66: Не заполнено | F66: Версии ПО | G66: Высокий | H66: =IF(D66="Не применимо",0,IF(G66="высокий",5,IF(G66="средний",3,IF(G66="низкий",1,"")))) -> 5 | I66: =IF(D66="Не применимо",0,IF(D66="Выполняется",1,IF(D66="Частично выполняется",0.5,IF(D66="Не выполняется",0,IF(D66="Не заполнено",0,""))))) -> 0 | J66: =I66*H66 -> 0 | K66: - | L66: 1.2.2 | M66: - | N66: - | P66: УБИ.225
A67: Orch-2-8 | B67: Настроены параметры аудита сред оркестрации (k8s audit policy), логи передаются и анализируются в SIEM | C67: 2 | D67: Не заполнено | F67: События ИБ | G67: Высокий | H67: =IF(D67="Не применимо",0,IF(G67="высокий",5,IF(G67="средний",3,IF(G67="низкий",1,"")))) -> 5 | I67: =IF(D67="Не применимо",0,IF(D67="Выполняется",1,IF(D67="Частично выполняется",0.5,IF(D67="Не выполняется",0,IF(D67="Не заполнено",0,""))))) -> 0 | J67: =I67*H67 -> 0 | K67: 1.2.16; 1.2.17; 1.2.18; 1.2.19; 3.2.1 | L67: 1.1.3; 1.1.4; 1.1.5; 1.1.6; 1.1.7; 1.1.8; 1.1.9; 1.1.10; 1.1.11; 1.1.12; 1.1.13; 1.1.14; 1.1.15; 1.1.16; 1.1.17; 1.1.18 | M67: - | N67: - | O67: 12.3 13.1 | P67: УБИ.223
A68: Orch-2-9 | B68: Определен список возможных инцидентов ИБ в части оркестратора | C68: 2 | D68: Не заполнено | F68: События ИБ | G68: Высокий | H68: =IF(D68="Не применимо",0,IF(G68="высокий",5,IF(G68="средний",3,IF(G68="низкий",1,"")))) -> 5 | I68: =IF(D68="Не применимо",0,IF(D68="Выполняется",1,IF(D68="Частично выполняется",0.5,IF(D68="Не выполняется",0,IF(D68="Не заполнено",0,""))))) -> 0 | J68: =I68*H68 -> 0 | K68: 3.2.2 | L68: - | M68: - | N68: -
A69: Orch-2-10 | B69: При администрировании оркестратора используется ролевая модель, при назначении прав используется принцип минимальных привилегий | C69: 2 | D69: Не заполнено | F69: Аутентификация и авторизация | G69: Высокий | H69: =IF(D69="Не применимо",0,IF(G69="высокий",5,IF(G69="средний",3,IF(G69="низкий",1,"")))) -> 5 | I69: =IF(D69="Не применимо",0,IF(D69="Выполняется",1,IF(D69="Частично выполняется",0.5,IF(D69="Не выполняется",0,IF(D69="Не заполнено",0,""))))) -> 0 | J69: =I69*H69 -> 0 | K69: 1.2.8; 5.1.1; 5.1.2; 5.1.3; 5.1.4; 5.1.5; 5.1.6; 5.1.7; 5.1.8; 5.1.9; 5.1.10; 5.1.11; 5.1.12; 5.1.13 | L69: 2.12 | M69: - | N69: - | O69: 14.2 14.3
A70: Orch-2-11 | B70: Для аутентификации в оркестраторе используется внешний сервис, например Active Directory | C70: 2 | D70: Не заполнено | F70: Аутентификация и авторизация | G70: Высокий | H70: =IF(D70="Не применимо",0,IF(G70="высокий",5,IF(G70="средний",3,IF(G70="низкий",1,"")))) -> 5 | I70: =IF(D70="Не применимо",0,IF(D70="Выполняется",1,IF(D70="Частично выполняется",0.5,IF(D70="Не выполняется",0,IF(D70="Не заполнено",0,""))))) -> 0 | J70: =I70*H70 -> 0 | K70: 3.1.1; 3.1.2; 3.1.3 | L70: - | M70: - | N70: - | O70: 15.1
A71: Orch-2-12 | B71: Процесс установки обновлений безопасности оркестратора регламентирован | C71: 2 | D71: Не заполнено | F71: Версии ПО | G71: Средний | H71: =IF(D71="Не применимо",0,IF(G71="высокий",5,IF(G71="средний",3,IF(G71="низкий",1,"")))) -> 3 | I71: =IF(D71="Не применимо",0,IF(D71="Выполняется",1,IF(D71="Частично выполняется",0.5,IF(D71="Не выполняется",0,IF(D71="Не заполнено",0,""))))) -> 0 | J71: =I71*H71 -> 0 | K71: - | L71: 1.2.2 | M71: - | N71: -
A72: Orch-2-13 | B72: Используются Policy engine или Admission controller, позволяющие контролировать конфигурацию запускаемых микросервисов | C72: 2 | D72: Не заполнено | F72: Контроль манифестов | G72: Высокий | H72: =IF(D72="Не применимо",0,IF(G72="высокий",5,IF(G72="средний",3,IF(G72="низкий",1,"")))) -> 5 | I72: =IF(D72="Не применимо",0,IF(D72="Выполняется",1,IF(D72="Частично выполняется",0.5,IF(D72="Не выполняется",0,IF(D72="Не заполнено",0,""))))) -> 0 | J72: =I72*H72 -> 0 | K72: 5.2.1 | L72: - | M72: - | N72: - | P72: УБИ.223 УБИ.224 УБИ.225
A73: Orch-3-1 | B73: Admission controller NamespaceLifecycle активирован и используется | C73: 3 | D73: Не заполнено | E73: =(COUNTIF(D73:D79,$D$180)+(COUNTIF(D73:D79,$D$183)*0.5))/(COUNTA(D73:D79)-COUNTIF(D73:D79,$D$182)) -> 0 | F73: Харденинг | G73: Низкий | H73: =IF(D73="Не применимо",0,IF(G73="высокий",5,IF(G73="средний",3,IF(G73="низкий",1,"")))) -> 1 | I73: =IF(D73="Не применимо",0,IF(D73="Выполняется",1,IF(D73="Частично выполняется",0.5,IF(D73="Не выполняется",0,IF(D73="Не заполнено",0,""))))) -> 0 | J73: =I73*H73 -> 0 | K73: 1.2.13 | L73: - | M73: - | N73: -
A74: Orch-3-2 | B74: Процесс настройки параметров безопасности среды контейнерной оркестрации регламентирован, используются стандарты безопасного конфигурирования | C74: 3 | D74: Не заполнено | F74: Харденинг | G74: Средний | H74: =IF(D74="Не применимо",0,IF(G74="высокий",5,IF(G74="средний",3,IF(G74="низкий",1,"")))) -> 3 | I74: =IF(D74="Не применимо",0,IF(D74="Выполняется",1,IF(D74="Частично выполняется",0.5,IF(D74="Не выполняется",0,IF(D74="Не заполнено",0,""))))) -> 0 | J74: =I74*H74 -> 0 | K74: - | L74: - | M74: - | N74: -
A75: Orch-3-3 | B75: Используется ротация сертификатов kubelet | C75: 3 | D75: Не заполнено | F75: Харденинг | G75: Средний | H75: =IF(D75="Не применимо",0,IF(G75="высокий",5,IF(G75="средний",3,IF(G75="низкий",1,"")))) -> 3 | I75: =IF(D75="Не применимо",0,IF(D75="Выполняется",1,IF(D75="Частично выполняется",0.5,IF(D75="Не выполняется",0,IF(D75="Не заполнено",0,""))))) -> 0 | J75: =I75*H75 -> 0 | K75: 4.2.10; 4.2.11 | L75: - | M75: - | N75: -
A76: Orch-3-4 | B76: База данных etcd шифруется | C76: 3 | D76: Не заполнено | F76: Харденинг | G76: Низкий | H76: =IF(D76="Не применимо",0,IF(G76="высокий",5,IF(G76="средний",3,IF(G76="низкий",1,"")))) -> 1 | I76: =IF(D76="Не применимо",0,IF(D76="Выполняется",1,IF(D76="Частично выполняется",0.5,IF(D76="Не выполняется",0,IF(D76="Не заполнено",0,""))))) -> 0 | J76: =I76*H76 -> 0 | K76: 1.2.27; 1.2.28; 2.1; 2.2; 2.3; 2.4; 2.5; 2.6; 2.7; 2.8 | L76: - | M76: - | N76: -
A77: Orch-3-5 | B77: Используется мониторинг ИТ состояние сред контейнеризации | C77: 3 | D77: Не заполнено | F77: Мониторинг | G77: Высокий | H77: =IF(D77="Не применимо",0,IF(G77="высокий",5,IF(G77="средний",3,IF(G77="низкий",1,"")))) -> 5 | I77: =IF(D77="Не применимо",0,IF(D77="Выполняется",1,IF(D77="Частично выполняется",0.5,IF(D77="Не выполняется",0,IF(D77="Не заполнено",0,""))))) -> 0 | J77: =I77*H77 -> 0 | K77: - | L77: 2.13; 5.27; 6.2 | M77: - | N77: -
A78: Orch-3-6 | B78: Используются отдельные решения по хранению секретов | C78: 3 | D78: Не заполнено | F78: Защита секретов | G78: Средний | H78: =IF(D78="Не применимо",0,IF(G78="высокий",5,IF(G78="средний",3,IF(G78="низкий",1,"")))) -> 3 | I78: =IF(D78="Не применимо",0,IF(D78="Выполняется",1,IF(D78="Частично выполняется",0.5,IF(D78="Не выполняется",0,IF(D78="Не заполнено",0,""))))) -> 0 | J78: =I78*H78 -> 0 | K78: 5.4.2 | L78: 7.4 | M78: - | N78: -
A79: Orch-3-7 | B79: Все соединения между сервисами шифруются при помощи mTLS | C79: 3 | D79: Не заполнено | F79: Харденинг | G79: Средний | H79: =IF(D79="Не применимо",0,IF(G79="высокий",5,IF(G79="средний",3,IF(G79="низкий",1,"")))) -> 3 | I79: =IF(D79="Не применимо",0,IF(D79="Выполняется",1,IF(D79="Частично выполняется",0.5,IF(D79="Не выполняется",0,IF(D79="Не заполнено",0,""))))) -> 0 | J79: =I79*H79 -> 0
A80: Orch-4-1 | B80: Используются стандарты безопасности на основе CIS Benchmark | C80: 4 | D80: Не заполнено | E80: =(COUNTIF(D80:D82,$D$180)+(COUNTIF(D80:D82,$D$183)*0.5))/(COUNTA(D80:D82)-COUNTIF(D80:D82,$D$182)) -> 0 | F80: Харденинг | G80: Средний | H80: =IF(D80="Не применимо",0,IF(G80="высокий",5,IF(G80="средний",3,IF(G80="низкий",1,"")))) -> 3 | I80: =IF(D80="Не применимо",0,IF(D80="Выполняется",1,IF(D80="Частично выполняется",0.5,IF(D80="Не выполняется",0,IF(D80="Не заполнено",0,""))))) -> 0 | J80: =I80*H80 -> 0 | K80: All | L80: All | M80: - | N80: -
A81: Orch-4-2 | B81: При хранении настроек и развертывании оркестратора используется подход IaC | C81: 4 | D81: Не заполнено | F81: IaC | G81: Средний | H81: =IF(D81="Не применимо",0,IF(G81="высокий",5,IF(G81="средний",3,IF(G81="низкий",1,"")))) -> 3 | I81: =IF(D81="Не применимо",0,IF(D81="Выполняется",1,IF(D81="Частично выполняется",0.5,IF(D81="Не выполняется",0,IF(D81="Не заполнено",0,""))))) -> 0 | J81: =I81*H81 -> 0 | K81: - | L81: - | M81: - | N81: -
A82: Orch-4-3 | B82: Для размещения etcd используются выделенные серверы с отдельной БД. Обеспечивается отказоустойчивость | C82: 4 | D82: Не заполнено | F82: Харденинг | G82: Низкий | H82: =IF(D82="Не применимо",0,IF(G82="высокий",5,IF(G82="средний",3,IF(G82="низкий",1,"")))) -> 1 | I82: =IF(D82="Не применимо",0,IF(D82="Выполняется",1,IF(D82="Частично выполняется",0.5,IF(D82="Не выполняется",0,IF(D82="Не заполнено",0,""))))) -> 0 | J82: =I82*H82 -> 0 | K82: - | L82: - | M82: - | N82: -
G83: Максимальный балл | H83: =SUM(H49:H82) -> 132 | I83: Итоговый общий балл | J83: =SUM(J49:J82) -> 0
A84: Безопасность сред контейнеризации Docker
A85: Dock-1-1 | B85: Установлен уровень логирования docker демона - info | C85: 1 | D85: Не заполнено | E85: =(COUNTIF(D85:D91,$D$180)+(COUNTIF(D85:D91,$D$183)*0.5))/(COUNTA(D85:D91)-COUNTIF(D85:D91,$D$182)) -> 0 | F85: Мониторинг | G85: Средний | H85: =IF(D85="Не применимо",0,IF(G85="высокий",5,IF(G85="средний",3,IF(G85="низкий",1,"")))) -> 3 | I85: =IF(D85="Не применимо",0,IF(D85="Выполняется",1,IF(D85="Частично выполняется",0.5,IF(D85="Не выполняется",0,IF(D85="Не заполнено",0,""))))) -> 0 | J85: =I85*H85 -> 0 | K85: - | L85: 2.3 | M85: - | N85: -
A86: Dock-1-2 | B86: Демон Docker имеет необходимые права для внесения изменений в iptables | C86: 1 | D86: Не заполнено | F86: Харденинг | G86: Высокий | H86: =IF(D86="Не применимо",0,IF(G86="высокий",5,IF(G86="средний",3,IF(G86="низкий",1,"")))) -> 5 | I86: =IF(D86="Не применимо",0,IF(D86="Выполняется",1,IF(D86="Частично выполняется",0.5,IF(D86="Не выполняется",0,IF(D86="Не заполнено",0,""))))) -> 0 | J86: =I86*H86 -> 0 | K86: - | L86: 2.4 | M86: - | N86: -
A87: Dock-1-3 | B87: В продуктивной среде не используются функции Docker, помеченные как экспериментальные | C87: 1 | D87: Не заполнено | F87: Харденинг | G87: Высокий | H87: =IF(D87="Не применимо",0,IF(G87="высокий",5,IF(G87="средний",3,IF(G87="низкий",1,"")))) -> 5 | I87: =IF(D87="Не применимо",0,IF(D87="Выполняется",1,IF(D87="Частично выполняется",0.5,IF(D87="Не выполняется",0,IF(D87="Не заполнено",0,""))))) -> 0 | J87: =I87*H87 -> 0 | K87: - | L87: 2.18 | M87: - | N87: -
A88: Dock-1-4 | B88: Устаревший драйвер для хранилищ данных aufs не используется в Docker | C88: 1 | D88: Не заполнено | F88: Харденинг | G88: Средний | H88: =IF(D88="Не применимо",0,IF(G88="высокий",5,IF(G88="средний",3,IF(G88="низкий",1,"")))) -> 3 | I88: =IF(D88="Не применимо",0,IF(D88="Выполняется",1,IF(D88="Частично выполняется",0.5,IF(D88="Не выполняется",0,IF(D88="Не заполнено",0,""))))) -> 0 | J88: =I88*H88 -> 0 | K88: - | L88: 2.6 | M88: - | N88: -
A89: Dock-1-5 | B89: Определена единая cgroup (control group) по умолчанию для всех контейнеров | C89: 1 | D89: Не заполнено | F89: Харденинг | G89: Высокий | H89: =IF(D89="Не применимо",0,IF(G89="высокий",5,IF(G89="средний",3,IF(G89="низкий",1,"")))) -> 5 | I89: =IF(D89="Не применимо",0,IF(D89="Выполняется",1,IF(D89="Частично выполняется",0.5,IF(D89="Не выполняется",0,IF(D89="Не заполнено",0,""))))) -> 0 | J89: =I89*H89 -> 0 | K89: - | L89: 2.10 | M89: - | N89: - | O89: 9.1
A90: Dock-1-6 | B90: Установлена опция --live-restore для демона Docker | C90: 1 | D90: Не заполнено | F90: Харденинг | G90: Средний | H90: =IF(D90="Не применимо",0,IF(G90="высокий",5,IF(G90="средний",3,IF(G90="низкий",1,"")))) -> 3 | I90: =IF(D90="Не применимо",0,IF(D90="Выполняется",1,IF(D90="Частично выполняется",0.5,IF(D90="Не выполняется",0,IF(D90="Не заполнено",0,""))))) -> 0 | J90: =I90*H90 -> 0 | K90: - | L90: 2.15 | M90: - | N90: -
A91: Dock-1-7 | B91: Настроены лимиты (ulimits) для контейнеров по умолчанию | C91: 2 | D91: Не заполнено | F91: Харденинг | G91: Низкий | H91: =IF(D91="Не применимо",0,IF(G91="высокий",5,IF(G91="средний",3,IF(G91="низкий",1,"")))) -> 1 | I91: =IF(D91="Не применимо",0,IF(D91="Выполняется",1,IF(D91="Частично выполняется",0.5,IF(D91="Не выполняется",0,IF(D91="Не заполнено",0,""))))) -> 0 | J91: =I91*H91 -> 0 | K91: - | L91: 2.8 | M91: - | N91: - | O91: 11
A92: Dock-2-1 | B92: Для сред контейнеризации на базе Docker используются средства мониторинг событий ИБ (локальный сервис) | C92: 2 | D92: Не заполнено | E92: =(COUNTIF(D92:D105,$D$180)+(COUNTIF(D92:D105,$D$183)*0.5))/(COUNTA(D92:D105)-COUNTIF(D92:D105,$D$182)) -> 0 | F92: События ИБ | G92: Высокий | H92: =IF(D92="Не применимо",0,IF(G92="высокий",5,IF(G92="средний",3,IF(G92="низкий",1,"")))) -> 5 | I92: =IF(D92="Не применимо",0,IF(D92="Выполняется",1,IF(D92="Частично выполняется",0.5,IF(D92="Не выполняется",0,IF(D92="Не заполнено",0,""))))) -> 0 | J92: =I92*H92 -> 0 | K92: - | L92: 1.1.3 | M92: - | N92: -
A93: Dock-2-2 | B93: Настроен аудит для ключевых файлов, относящихся к демону Docker | C93: 2 | D93: Не заполнено | F93: Мониторинг | G93: Высокий | H93: =IF(D93="Не применимо",0,IF(G93="высокий",5,IF(G93="средний",3,IF(G93="низкий",1,"")))) -> 5 | I93: =IF(D93="Не применимо",0,IF(D93="Выполняется",1,IF(D93="Частично выполняется",0.5,IF(D93="Не выполняется",0,IF(D93="Не заполнено",0,""))))) -> 0 | J93: =I93*H93 -> 0 | K93: - | L93: 1.1.4; 1.1.5; 1.1.6; 1.1.7; 1.1.8; 1.1.9; 1.1.10; 1.1.11; 1.1.12; 1.1.13; 1.1.14; 1.1.15; 1.1.16; 1.1.17; 1.1.18 | M93: - | N93: - | O93: 12.2 | Q93: Директории /run/containerd /var/lib/docker /etc/docker Файлы сontainerd.sock docker.sock /etc/default/docker /etc/docker/daemon.json /etc/containerd/config.toml /etc/sysconfig/docker /usr/bin/containerd /usr/bin/containerd-shim usr/bin/containerd-shim-runc-v1 /usr/bin/containerd-shim-runc-v2 /usr/bin/runc
A94: Dock-2-3 | B94: hairpin NAT mode используется для публикации сервисов вместо userland proxy service | C94: 2 | D94: Не заполнено | F94: Харденинг | G94: Средний | H94: =IF(D94="Не применимо",0,IF(G94="высокий",5,IF(G94="средний",3,IF(G94="низкий",1,"")))) -> 3 | I94: =IF(D94="Не применимо",0,IF(D94="Выполняется",1,IF(D94="Частично выполняется",0.5,IF(D94="Не выполняется",0,IF(D94="Не заполнено",0,""))))) -> 0 | J94: =I94*H94 -> 0 | K94: - | L94: 2.16 | M94: - | N94: - | Q94: /etc/docker/daemon.json - --userland-proxy=false
A95: Dock-2-4 | B95: Разрешения на конфигурационные файлы, хранящиеся на узлах worker соответствуют лучшим практикам CIS | C95: 2 | D95: Не заполнено | F95: Харденинг | G95: Средний | H95: =IF(D95="Не применимо",0,IF(G95="высокий",5,IF(G95="средний",3,IF(G95="низкий",1,"")))) -> 3 | I95: =IF(D95="Не применимо",0,IF(D95="Выполняется",1,IF(D95="Частично выполняется",0.5,IF(D95="Не выполняется",0,IF(D95="Не заполнено",0,""))))) -> 0 | J95: =I95*H95 -> 0 | K95: - | L95: 3.1; 3.2; 3.3; 3.4; 3.5; 3.6; 3.7; 3.8; 3.9; 3.10; 3.11; 3.12; 3.13; 3.14; 3.15; 3.16; 3.17; 3.18; 3.19; 3.20; 3.21; 3.22; 3.23; 3.24 | M95: - | N95: -
A96: Dock-2-5 | B96: Используются версии оркестратора, поддерживаемые производителем. Для неподдерживаемых версий ОС имеется расширенная поддержка | C96: 2 | D96: Не заполнено | F96: Версии ПО | G96: Высокий | H96: =IF(D96="Не применимо",0,IF(G96="высокий",5,IF(G96="средний",3,IF(G96="низкий",1,"")))) -> 5 | I96: =IF(D96="Не применимо",0,IF(D96="Выполняется",1,IF(D96="Частично выполняется",0.5,IF(D96="Не выполняется",0,IF(D96="Не заполнено",0,""))))) -> 0 | J96: =I96*H96 -> 0 | K96: - | L96: 1.2.2 | M96: - | N96: - | P96: УБИ.225
A97: Dock-2-6 | B97: Определен список возможных инцидентов ИБ в части оркестратора | C97: 2 | D97: Не заполнено | F97: События ИБ | G97: Высокий | H97: =IF(D97="Не применимо",0,IF(G97="высокий",5,IF(G97="средний",3,IF(G97="низкий",1,"")))) -> 5 | I97: =IF(D97="Не применимо",0,IF(D97="Выполняется",1,IF(D97="Частично выполняется",0.5,IF(D97="Не выполняется",0,IF(D97="Не заполнено",0,""))))) -> 0 | J97: =I97*H97 -> 0 | K97: - | L97: - | M97: - | N97: -
A98: Dock-2-7 | B98: Производится регулярная очистка неиспользуемых образов на хостах | C98: 2 | D98: Не заполнено | F98: Харденинг | G98: Высокий | H98: =IF(D98="Не применимо",0,IF(G98="высокий",5,IF(G98="средний",3,IF(G98="низкий",1,"")))) -> 5 | I98: =IF(D98="Не применимо",0,IF(D98="Выполняется",1,IF(D98="Частично выполняется",0.5,IF(D98="Не выполняется",0,IF(D98="Не заполнено",0,""))))) -> 0 | J98: =I98*H98 -> 0 | K98: - | L98: 6.1 | M98: - | N98: -
A99: Dock-2-8 | B99: Процесс установки обновлений безопасности Docker регламентирован | C99: 2 | D99: Не заполнено | F99: Версии ПО | G99: Средний | H99: =IF(D99="Не применимо",0,IF(G99="высокий",5,IF(G99="средний",3,IF(G99="низкий",1,"")))) -> 3 | I99: =IF(D99="Не применимо",0,IF(D99="Выполняется",1,IF(D99="Частично выполняется",0.5,IF(D99="Не выполняется",0,IF(D99="Не заполнено",0,""))))) -> 0 | J99: =I99*H99 -> 0 | K99: - | L99: 1.2.2 | M99: - | N99: -
A100: Dock-2-9 | B100: Используется средство контроля параметров запускаемых контейнеров | C100: 2 | D100: Не заполнено | F100: Харденинг | G100: Высокий | H100: =IF(D100="Не применимо",0,IF(G100="высокий",5,IF(G100="средний",3,IF(G100="низкий",1,"")))) -> 5 | I100: =IF(D100="Не применимо",0,IF(D100="Выполняется",1,IF(D100="Частично выполняется",0.5,IF(D100="Не выполняется",0,IF(D100="Не заполнено",0,""))))) -> 0 | J100: =I100*H100 -> 0 | K100: - | L100: - | M100: - | N100: - | O100: 11 | Q100: OPA GateKeeper /etc/docker/daemon.json наличие плагина OPA или аналог
...

Sheet Уровни зрелости (другой вид)
A1: Домен | B1: ID | C1: Level0 - Unitiated | D1: ID | E1: Level1 - Beginners | F1: ID | G1: Level2 - Intermediate | H1: ID | I1: Level3 - Advanced | J1: ID | K1: Level4 - Experts
A2: Общие практики безопасности (Gen) | B2: Gen-0-1 | C2: Базовые контроли не выполняются | D2: =Практики!A3 -> Gen-1-1 | E2: =Практики!B3 -> Создаются резервные копии критичных серверов, процесс резервирования является системным. | F2: =Практики!A7 -> Gen-2-1 | G2: =Практики!B7 -> Удаленный доступ подрядчиков регламентирован, права минимально необходимы и контролируется. | H2: =Практики!A11 -> Gen-3-1 | I2: =Практики!B11 -> Тестовая среда располагается в отдельном сетевом сегменте. Доступ к среде ограничен | J2: =Практики!A13 -> Gen-4-1 | K2: =Практики!B13 -> Обеспечена отказоустойчивость серверной инфраструктуры в рамках нескольких сайтов
D3: =Практики!A4 -> Gen-1-2 | E3: =Практики!B4 -> Должна быть обеспечена отказоустойчивость серверной инфраструктуры в рамках 1 сайта | F3: =Практики!A8 -> Gen-2-2 | G3: =Практики!B8 -> Зоны распределения ответственности администраторов разграничены и задокументированы для оркестратора и ОС | H3: =Практики!A12 -> Gen-3-2 | I3: =Практики!B12 -> Проводятся учения по отработке плана аварийного восстановления с фактическим прохождением этапов восстановления на условно аварийном сервере
D4: =Практики!A5 -> Gen-1-3 | E4: =Практики!B5 -> Выполняется контроль сетевого трафика на уровне межсетевых экранов (L3/L4) в PROD сегменте (доступ к узлам) | F4: =Практики!A9 -> Gen-2-3 | G4: =Практики!B9 -> Процесс резервного копирования регламентирован
D5: =Практики!A6 -> Gen-1-4 | E5: =Практики!B6 -> PROD инфраструктура находится в выделенном сетевом сегменте | F5: =Практики!A10 -> Gen-2-4 | G5: =Практики!B10 -> Процесс восстановления доступности регламентирован
A6: Безопасность nodes (Nodes) | B6: Nodes-0-1 | C6: Стандарты безопасности для узлов не применяются | D6: =Практики!A16 -> Nodes-1-1 | E6: =Практики!B16 -> УЗ администраторов ОС серверов должны содержать уникальный идентификатор, позволяющий связать администратора с их действиями в ОС | F6: =Практики!A23 -> Nodes-2-1 | G6: =Практики!B23 -> Привилегированные права в ОС имеют только УЗ, которым такой доступ необходим, данные УЗ актуальны | H6: =Практики!A36 -> Nodes-3-1 | I6: =Практики!B36 -> Процесс установки обновлений безопасности ОС регламентирован | J6: =Практики!A43 -> Nodes-4-1 | K6: =Практики!B43 -> Применяется шифрование диска
D7: =Практики!A17 -> Nodes-1-2 | E7: =Практики!B17 -> УЗ root не должна использоваться для администрирования ОС | F7: =Практики!A24 -> Nodes-2-2 | G7: =Практики!B24 -> Установлены актуальные обновления безопасности ОС, процесс обновления является системным | H7: =Практики!A37 -> Nodes-3-2 | I7: =Практики!B37 -> Проводится сканирование «золотого» образа ОС на уязвимости | J7: =Практики!A44 -> Nodes-4-2 | K7: =Практики!B44 -> Должны использоваться специально настроенные АРМ (SAW/PAW – закрытая рабочая станция с высоким уровнем защиты) для администрирования инфраструктуры
D8: =Практики!A18 -> Nodes-1-3 | E8: =Практики!B18 -> Используются версии ОС, поддерживаемые производителем. Для неподдерживаемых версий ОС имеется расширенная поддержка | F8: =Практики!A25 -> Nodes-2-3 | G8: =Практики!B25 -> Проводятся периодические сканирования ОС, направленные на выявление уязвимостей | H8: =Практики!A38 -> Nodes-3-3 | I8: =Практики!B38 -> Процесс настройки параметров безопасности ОС регламентирован, используются стандарты безопасного конфигурирования c минимальным количеством параметров | J8: =Практики!A45 -> Nodes-4-3 | K8: =Практики!B45 -> Используются стандарты безопасности, включающие в себя большую часть настроек на основе CIS Benchmark
D9: =Практики!A19 -> Nodes-1-4 | E9: =Практики!B19 -> Осуществляется сбор логов о состоянии серверов (мониторинг ИТ) - собираются данные о состоянии сервера. | F9: =Практики!A26 -> Nodes-2-4 | G9: =Практики!B26 -> Для установки ОС используется «золотой» образ | H9: =Практики!A39 -> Nodes-3-4 | I9: =Практики!B39 -> Включен хостовый МЭ и настроен в соответствии с правилом «запрещено все, что не разрешено» | J9: =Практики!A46 -> Nodes-4-4 | K9: =Практики!B46 -> При хранении настроек и развертывании ОС используется подход IaC
D10: =Практики!A20 -> Nodes-1-5 | E10: =Практики!B20 -> Используется антивирусное ПО с постоянно обновляемыми базами. | F10: =Практики!A27 -> Nodes-2-5 | G10: =Практики!B27 -> Обновления ОС для серверов, содержащих критичную информацию, устанавливаются только после предварительного успешного тестирования на специально выделенном стенде | H10: =Практики!A40 -> Nodes-3-5 | I10: =Практики!B40 -> Определен перечень базовых СЗИ, устанавливаемых на серверы (помимо антивируса)
D11: =Практики!A21 -> Nodes-1-6 | E11: =Практики!B21 -> Реализованы механизмы синхронизации времени в ОС с целью возможности подтверждения времени записи событий | F11: =Практики!A28 -> Nodes-2-6 | G11: =Практики!B28 -> Проводятся регулярные сканирования антивирусом | H11: =Практики!A41 -> Nodes-3-6 | I11: =Практики!B41 -> Проводятся на регулярной основе внутренние аудиты ИБ конфигурационных настроек ОС
D12: =Практики!A22 -> Nodes-1-7 | E12: =Практики!B22 -> Выполнены настройки сложности пароля: Возможность использования пустых паролей - нет длина пароля: 14; сложность: да; срок действия: не более года; блокирование известных паролей: 20 и более из ТОП, 5 ранее использованных; | F12: =Практики!A29 -> Nodes-2-7 | G12: =Практики!B29 -> Используются базовые настройки безопасности для ОС: - выполнен харденинг SSH: LoginGraceTime = 1 m; PermitRootLogin = no; MaxAuthTries = 6; IgnoreRhosts = yes; UsePAM = yes; TCPKeepAlive = yes; X11Forwarding = no; ClientAliveInterval = 600; ClientAliveCountMax = 3 | H12: =Практики!A42 -> Nodes-3-7 | I12: =Практики!B42 -> Небезопасные службы ОС (стандартные службы, например, telnet и нестандартные службы - службы стороннего ПО для удаленного доступа и т.д.) отсутствуют или отключены
F13: =Практики!A30 -> Nodes-2-8 | G13: =Практики!B30 -> Логин на сервер только через SSH ключ
F14: =Практики!A31 -> Nodes-2-9 | G14: =Практики!B31 -> Определены и настроены критичные события, которые должны собираться с *nix-серверов (перечень параметров). События передаются и анализируются в SIEM
F15: =Практики!A32 -> Nodes-2-10 | G15: =Практики!B32 -> Определен список возможных инцидентов ИБ в части ОС
F16: =Практики!A33 -> Nodes-2-11 | G16: =Практики!B33 -> Выполняется ревизия УЗ администраторов ОС. В случае необходимости, УЗ деактивируется или отключается
F17: =Практики!A34 -> Nodes-2-12 | G17: =Практики!B34 -> Неразрешенное ПО или не требуемое для администрирования на ОС хост-серверов не установлено
F18: =Практики!A35 -> Nodes-2-13 | G18: =Практики!B35 -> Для размещения контейнеров на дисковой подсистеме используется отдельная партиция
A19: Безопасность оркестратора (Orch) | B19: Orch-0-1 | C19: Стандарты безопасности оркестраторов не применяются | D19: =Практики!A49 -> Orch-1-1 | E19: =Практики!B49 -> Для доступа к kube-apiserver используется аутентификация и авторизация | F19: =Практики!A60 -> Orch-2-1 | G19: =Практики!B60 -> УЗ администраторов оркестратора подвергаются ревизии. В случае необходимости, УЗ деактивируются или отключаются | H19: =Практики!A73 -> Orch-3-1 | I19: =Практики!B73 -> Admission controller NamespaceLifecycle активирован и используется | J19: =Практики!A80 -> Orch-4-1 | K19: =Практики!B80 -> Используются стандарты безопасности на основе CIS Benchmark
D20: =Практики!A50 -> Orch-1-2 | E20: =Практики!B50 -> Для доступа к kube-apiserver не используется базовая аутентификация | F20: =Практики!A61 -> Orch-2-2 | G20: =Практики!B61 -> Установлены актуальные обновления безопасности оркестратора, процесс обновления является системным | H20: =Практики!A74 -> Orch-3-2 | I20: =Практики!B74 -> Процесс настройки параметров безопасности среды контейнерной оркестрации регламентирован, используются стандарты безопасного конфигурирования | J20: =Практики!A81 -> Orch-4-2 | K20: =Практики!B81 -> При хранении настроек и развертывании оркестратора используется подход IaC
D21: =Практики!A51 -> Orch-1-3 | E21: =Практики!B51 -> УЗ администраторов Kubernetes должны содержать уникальный идентификатор, позволяющий связать администратора с их действиями в среде контейнерной оркестрации | F21: =Практики!A62 -> Orch-2-3 | G21: =Практики!B62 -> УЗ cluster-admin не используется для администрирования кластеров Kubernetes | H21: =Практики!A75 -> Orch-3-3 | I21: =Практики!B75 -> Используется ротация сертификатов kubelet | J21: =Практики!A82 -> Orch-4-3 | K21: =Практики!B82 -> Для размещения etcd используются выделенные серверы с отдельной БД. Обеспечивается отказоустойчивость
D22: =Практики!A52 -> Orch-1-4 | E22: =Практики!B52 -> Для доступа к kube-apiserver используется только защищенное TLS соединение | F22: =Практики!A63 -> Orch-2-4 | G22: =Практики!B63 -> Admission controller AlwaysPullImages активирован и используется | H22: =Практики!A76 -> Orch-3-4 | I22: =Практики!B76 -> База данных etcd шифруется
D23: =Практики!A53 -> Orch-1-5 | E23: =Практики!B53 -> Для коммуникации между узлами кластера (master, worker, infrastructure) используются только шифрованные соединения TLS | F23: =Практики!A64 -> Orch-2-5 | G23: =Практики!B64 -> Разрешения на конфигурационные файлы, хранящиеся на узлах master соответствуют лучшим практикам CIS | H23: =Практики!A77 -> Orch-3-5 | I23: =Практики!B77 -> Используется мониторинг ИТ состояние сред контейнеризации
D24: =Практики!A54 -> Orch-1-6 | E24: =Практики!B54 -> Admission controller AlwaysAdmit не используется | F24: =Практики!A65 -> Orch-2-6 | G24: =Практики!B65 -> Разрешения на конфигурационные файлы, хранящиеся на узлах worker соответствуют лучшим практикам CIS | H24: =Практики!A78 -> Orch-3-6 | I24: =Практики!B78 -> Используются отдельные решения по хранению секретов
D25: =Практики!A55 -> Orch-1-7 | E25: =Практики!B55 -> Для доступа kube-apiserver к etcd используется аутентификация через сертификаты | F25: =Практики!A66 -> Orch-2-7 | G25: =Практики!B66 -> Используются версии оркестратора, поддерживаемые производителем. Для неподдерживаемых версий ОС имеется расширенная поддержка | H25: =Практики!A79 -> Orch-3-7 | I25: =Практики!B79 -> Все соединения между сервисами шифруются при помощи mTLS
D26: =Практики!A56 -> Orch-1-8 | E26: =Практики!B56 -> Анонимная аутентификация kubelet отключена | F26: =Практики!A67 -> Orch-2-8 | G26: =Практики!B67 -> Настроены параметры аудита сред оркестрации (k8s audit policy), логи передаются и анализируются в SIEM
D27: =Практики!A57 -> Orch-1-9 | E27: =Практики!B57 -> Read-only доступ к kubelet не используется | F27: =Практики!A68 -> Orch-2-9 | G27: =Практики!B68 -> Определен список возможных инцидентов ИБ в части оркестратора
D28: =Практики!A58 -> Orch-1-10 | E28: =Практики!B58 -> Для доступа к kubelet используется только шифрованный трафик TLS | F28: =Практики!A69 -> Orch-2-10 | G28: =Практики!B69 -> При администрировании оркестратора используется ролевая модель, при назначении прав используется принцип минимальных привилегий
D29: =Практики!A59 -> Orch-1-11 | E29: =Практики!B59 -> Используется webhook авторизация kubelet с использованием сертификата kube-apiserver | F29: =Практики!A70 -> Orch-2-11 | G29: =Практики!B70 -> Для аутентификации в оркестраторе используется внешний сервис, например Active Directory
F30: =Практики!A71 -> Orch-2-12 | G30: =Практики!B71 -> Процесс установки обновлений безопасности оркестратора регламентирован
F31: =Практики!A72 -> Orch-2-13 | G31: =Практики!B72 -> Используются Policy engine или Admission controller, позволяющие контролировать конфигурацию запускаемых микросервисов
A32: Безопасность сред контейнеризации Docker (Dock) | B32: Dock-0-1 | C32: Стандарты безопасности сред контейнеризации Docker не применяются | D32: =Практики!A85 -> Dock-1-1 | E32: =Практики!B85 -> Установлен уровень логирования docker демона - info | F32: =Практики!A92 -> Dock-2-1 | G32: =Практики!B92 -> Для сред контейнеризации на базе Docker используются средства мониторинг событий ИБ (локальный сервис) | H32: =Практики!A106 -> Dock-3-1 | I32: =Практики!B106 -> Настроены параметры аудита сред оркестрации, логи передаются и анализируются в SIEM | J32: =Практики!A115 -> Dock-4-1 | K32: =Практики!B115 -> Используются стандарты безопасности на основе CIS Benchmark (более 70% параметров) для оркестратора Docker
D33: =Практики!A86 -> Dock-1-2 | E33: =Практики!B86 -> Демон Docker имеет необходимые права для внесения изменений в iptables | F33: =Практики!A93 -> Dock-2-2 | G33: =Практики!B93 -> Настроен аудит для ключевых файлов, относящихся к демону Docker | H33: =Практики!A107 -> Dock-3-2 | I33: =Практики!B107 -> Доступ к демону Docker имеет ограниченное число пользователей ОС | J33: =Практики!A116 -> Dock-4-2 | K33: =Практики!B116 -> При хранении настроек и развертывании оркестратора используется подход IaC
D34: =Практики!A87 -> Dock-1-3 | E34: =Практики!B87 -> В продуктивной среде не используются функции Docker, помеченные как экспериментальные | F34: =Практики!A94 -> Dock-2-3 | G34: =Практики!B94 -> hairpin NAT mode используется для публикации сервисов вместо userland proxy service | H34: =Практики!A108 -> Dock-3-3 | I34: =Практики!B108 -> Контролируется целостность исполняемых файлов Docker, а также его конфигураций | J34: =Практики!A117 -> Dock-4-3 | K34: =Практики!B117 -> Используются самописные плагины для авторизации команд, поступающих к Docker демону
D35: =Практики!A88 -> Dock-1-4 | E35: =Практики!B88 -> Устаревший драйвер для хранилищ данных aufs не используется в Docker | F35: =Практики!A95 -> Dock-2-4 | G35: =Практики!B95 -> Разрешения на конфигурационные файлы, хранящиеся на узлах worker соответствуют лучшим практикам CIS | H35: =Практики!A109 -> Dock-3-4 | I35: =Практики!B109 -> Используется мониторинг ИТ состояния сред контейнеризации (не только ОС, но и сама среда контейнеризации) | J35: =Практики!A118 -> Dock-4-4 | K35: =Практики!B118 -> Трафик между контейнерами разделен (для разграничения доступа между контейнеров используется несколько сетевых мостов - Network Bridge)
D36: =Практики!A89 -> Dock-1-5 | E36: =Практики!B89 -> Определена единая cgroup (control group) по умолчанию для всех контейнеров | F36: =Практики!A96 -> Dock-2-5 | G36: =Практики!B96 -> Используются версии оркестратора, поддерживаемые производителем. Для неподдерживаемых версий ОС имеется расширенная поддержка | H36: =Практики!A110 -> Dock-3-5 | I36: =Практики!B110 -> Для сетевого доступа к Docker Daemon используется TLS-аутентификация по сертификату | J36: =Практики!A119 -> Dock-4-5 | K36: =Практики!B119 -> Определены отдельные cgroup (control group) для групп контейнеров
D37: =Практики!A90 -> Dock-1-6 | E37: =Практики!B90 -> Установлена опция --live-restore для демона Docker | F37: =Практики!A97 -> Dock-2-6 | G37: =Практики!B97 -> Определен список возможных инцидентов ИБ в части оркестратора | H37: =Практики!A111 -> Dock-3-6 | I37: =Практики!B111 -> Для доступа к Docker Daemon используется только защищенное TLS соединение | J37: =Практики!A120 -> Dock-4-6 | K37: =Практики!B120 -> В кластере SWARM используется режим auto-lock. Для запуска узлов необходимо ввести ключ разблокировки доступа к ключам шифрования
D38: =Практики!A91 -> Dock-1-7 | E38: =Практики!B91 -> Настроены лимиты (ulimits) для контейнеров по умолчанию | F38: =Практики!A98 -> Dock-2-7 | G38: =Практики!B98 -> Производится регулярная очистка неиспользуемых образов на хостах | H38: =Практики!A112 -> Dock-3-7 | I38: =Практики!B112 -> Демон Docker запущен в rootless-режиме | J38: =Практики!A121 -> Dock-4-7 | K38: =Практики!B121 -> Для ключей разблокировки режима auto-lock используется ротация
F39: =Практики!A99 -> Dock-2-8 | G39: =Практики!B99 -> Процесс установки обновлений безопасности Docker регламентирован
F40: =Практики!A100 -> Dock-2-9 | G40: =Практики!B100 -> Используется средство контроля параметров запускаемых контейнеров
F41: =Практики!A101 -> Dock-2-10 | G41: =Практики!B101 -> Процесс настройки параметров безопасности среды контейнерной оркестрации регламентирован, используются стандарты конфигурирования с базовыми стандартами
F42: =Практики!A102 -> Dock-2-11 | G42: =Практики!B102 -> Сервис Docker Swarm доступен только на тех сетевых интерфейсах, на которых это необходимо.
F43: =Практики!A103 -> Dock-2-12 | G43: =Практики!B103 -> Настроено шифрование для overlay сетей, используемых для связи между хост-серверами в кластере Docker SWARM
F44: =Практики!A104 -> Dock-2-13 | G44: =Практики!B104 -> Сертификат, используемый для коммуникации между узлами SWARM роитруется не реже 90 дней (значение по умолчанию)
F45: =Практики!A105 -> Dock-2-14 | G45: =Практики!B105 -> Минимальное необходимое количество узлов обладают ролью Manager. В общем случае - не более 3 (нечетное количество).
A46: Безопасность запускаемых приложений (IMG) | B46: IMG-0-1 | C46: Стандарты безопасности для сред контейнеризации не применяются | D46: =Практики!A124 -> IMG-1-1 | E46: =Практики!B124 -> В собранных образах не должны храниться секреты | F46: =Практики!A129 -> IMG-2-1 | G46: =Практики!B129 -> Образы контейнеров не должны содержать уязвимостей, которые возможно проэксплуатировать | H46: =Практики!A132 -> IMG-3-1 | I46: =Практики!B132 -> Для собираемых образов генерируется SBOM | J46: =Практики!A136 -> IMG-4-1 | K46: =Практики!B136 -> Должны использоваться образы, содержащие минимальный функционал (distroless)
D47: =Практики!A125 -> IMG-1-2 | E47: =Практики!B125 -> Контейнеры запускаются из образов, хранящихся в локальных репозиториях | F47: =Практики!A130 -> IMG-2-2 | G47: =Практики!B130 -> Выполняется сканирование образов контейнеров в CI/CD на наличие уязвимостей | H47: =Практики!A133 -> IMG-3-2 | I47: =Практики!B133 -> На образы регулярно устанавливаются обновления (обновляются базовые образы) | J47: =Практики!A137 -> IMG-4-2 | K47: =Практики!B137 -> Сборки в CI/CD блокируются при найденных уязвимостях в образах контейнеров по договоренности между ИБ и разработчиками
D48: =Практики!A126 -> IMG-1-3 | E48: =Практики!B126 -> Выполняется сканирование образов контейнеров. Запуск сканирования происходит в ручном режиме. | F48: =Практики!A131 -> IMG-2-3 | G48: =Практики!B131 -> При обнаружении дефектов ИБ в образах контейнеров автоматизированно создаются задачи на их устранение в тикет-системе | H48: =Практики!A134 -> IMG-3-3 | I48: =Практики!B134 -> Собираемые образы подписываются электронной подписью при сборке, а также осуществляется их проверка
D49: =Практики!A127 -> IMG-1-4 | E49: =Практики!B127 -> Осуществляется мультиуровневая сборка для минимизации размера образа и его функционала | H49: =Практики!A135 -> IMG-3-4 | I49: =Практики!B135 -> Выполняется периодическое сканирование образов контейнеров, размещенных во внутренних репозиториях, на наличие уязвимостей
D50: =Практики!A128 -> IMG-1-5 | E50: =Практики!B128 -> Осуществляется сканирование Docker файлов на недостатки конфигурации ИБ
A51: Безопасность запускаемых приложений (MAN) | B51: MAN-0-1 | C51: Стандарты безопасности для сред контейнеризации не применяются | D51: =Практики!A140 -> MAN-1-1 | E51: =Практики!B140 -> В манифестах не используются секреты в открытом виде | F51: =Практики!A144 -> MAN-2-1 | G51: =Практики!B144 -> В манифестах используются скрипты проверки доступности приложений | H51: =Практики!A152 -> MAN-3-1 | I51: =Практики!B152 -> Процесс настройки параметров безопасности манифестов регламентирован, используются базовые стандарты безопасного конфигурирования манифестов. | J51: =Практики!A156 -> MAN-4-1 | K51: =Практики!B156 -> Для групп контейнеров используются отдельные apparmor-профайлы
D52: =Практики!A141 -> MAN-1-2 | E52: =Практики!B141 -> В манифестах не используется флаг privileged для контейнеров | F52: =Практики!A145 -> MAN-2-2 | G52: =Практики!B145 -> В манифестах не используются тома (volume) типа host path | H52: =Практики!A153 -> MAN-3-2 | I52: =Практики!B153 -> Осуществляется контроль за выполнением команд внутри контейнера от пользователя root Настроены политики средства контроля запускаемых сущностей, ограничивающие запуск контейнеров с пользователем root | J52: =Практики!A157 -> MAN-4-2 | K52: =Практики!B157 -> Для групп контейнеров используются отдельные seccomp-профайлы
D53: =Практики!A142 -> MAN-1-3 | E53: =Практики!B142 -> В конфигурациях для контейнеров не используется host network (сеть хоста) | F53: =Практики!A146 -> MAN-2-3 | G53: =Практики!B146 -> В манифестах не используются образы контейнеров с тегом latest | H53: =Практики!A154 -> MAN-3-3 | I53: =Практики!B154 -> В конфигурациях deployments/replicasets/pods/daemonsets/statefulsets для контейнеров, используется read only корневая системы (readOnlyRootFilesystem)
D54: =Практики!A143 -> MAN-1-4 | E54: =Практики!B143 -> В манифестах не используются флаги allowPrivilegeEscalation или capabilities CAP_SYS_ADMIN | F54: =Практики!A147 -> MAN-2-4 | G54: =Практики!B147 -> В манифестах не монтируются чувствительные каталоги и файлы хостовой ОС | H54: =Практики!A155 -> MAN-3-4 | I54: =Практики!B155 -> Настроены политики средства контроля запускаемых сущностей, требующих в конфигурации указывать необходимые capabilities
F55: =Практики!A148 -> MAN-2-5 | G55: =Практики!B148 -> В манифестах не используются пространтсва имен PID, разделенные между хост-сервером и контейнером
F56: =Практики!A149 -> MAN-2-6 | G56: =Практики!B149 -> В манифестах не используются пространтсва имен IPC разделенные между хост-сервером и контейнером
F57: =Практики!A150 -> MAN-2-7 | G57: =Практики!B150 -> В манифестах не используются пространтсва имен разделенные UTS между хост-сервером и контейнером
F58: =Практики!A151 -> MAN-2-8 | G58: =Практики!B151 -> В манифестах настроены ограничения для контейнеров (limits и requests, ulimits или другая опция)
A59: Безопасность запускаемых приложений (CONT) | B59: CONT-0-1 | C59: Стандарты безопасности для сред контейнеризации не применяются | D59: =Практики!A160 -> CONT-1-1 | E59: =Практики!B160 -> Используются профили по умолчанию Secomp | F59: =Практики!A162 -> CONT-2-1 | G59: =Практики!B162 -> Используются сетевые политики для разграничения доступа между неймспейсами | H59: =Практики!A165 -> CONT-3-1 | I59: =Практики!B165 -> Используются сетевые политики для разграничения доступа между микросервисами | J59: =Практики!A171 -> CONT-4-1 | K59: =Практики!B171 -> Настроены и используются кастомизированные Runtime политики для отдельных контейнерных приложений в режиме block
D60: =Практики!A161 -> CONT-1-2 | E60: =Практики!B161 -> В контейнерах не запущен демон sshd | F60: =Практики!A163 -> CONT-2-2 | G60: =Практики!B163 -> Настроены и используются L7 сетевые политики контроля трафика в режиме мониторинга | H60: =Практики!A166 -> CONT-3-2 | I60: =Практики!B166 -> Настроены и используются L7 сетевые политики контроля трафика в режиме Block
F61: =Практики!A164 -> CONT-2-3 | G61: =Практики!B164 -> Осуществляется мониторинг запускаемых процессов, сетевых соединений и использования файлов в контейнерах. Используются правила по умолчанию | H61: =Практики!A167 -> CONT-3-3 | I61: =Практики!B167 -> Осуществляется мониторинг запускаемых процессов, сетевых соединений и использования файлов в контейнерах. Правила регулярно обновляются и учитывают актуальные угрозы
H62: =Практики!A168 -> CONT-3-4 | I62: =Практики!B168 -> Используются кастомизированные политики Runtime для сред контейнеризации, как минимум уровня всего кластера
H63: =Практики!A169 -> CONT-3-5 | I63: =Практики!B169 -> Используются профили seccomp, кастомизированные под микросервисы
H64: =Практики!A170 -> CONT-3-6 | I64: =Практики!B170 -> Используется мониторинг аномалий для запущенных контейнеров

Sheet CIS Docker
A1: ID в CIS Docker | B1: Требование | C1: Примечание | D1: JCSF
A2: Host Configuration
A3: Linux Host Specific Configuration
A4: 1.1.1 | B4: Ensure a separate partition for containers has been created | C4: All Docker containers and their data and metadata is stored under /var/lib/dockerdirectory. By default, /var/lib/docker should be mounted under either the / or /varpartitions dependent on how the Linux operating system in use is configured. | D4: DOCK-1-2
A5: 1.1.2 | B5: Ensure only trusted users are allowed to control Docker daemon | C5: The Docker daemon currently requires access to the Docker socket which is, by default, owned by the user root and the group docker. | D5: DOCK-3-2
A6: 1.1.3 | B6: Ensure auditing is configured for the Docker daemon | C6: Audit all Docker daemon activities. | D6: ORCH-2-8; DOCK-2-1
A7: 1.1.4 | B7: Ensure auditing is configured for Docker files and directories - /run/containerd | C7: Audit /run/containerd. | D7: ORCH-2-8; DOCK-2-2
A8: 1.1.5 | B8: Ensure auditing is configured for Docker files and directories - /var/lib/docker | C8: Audit /var/lib/docker. | D8: ORCH-2-8; DOCK-2-2
A9: 1.1.6 | B9: Ensure auditing is configured for Docker files and directories - /etc/docker | C9: Audit /etc/docker. | D9: ORCH-2-8; DOCK-2-2
A10: 1.1.7 | B10: Ensure auditing is configured for Docker files and directories - docker.service | C10: Audit the docker.service if applicable. | D10: ORCH-2-8; DOCK-2-2
A11: 1.1.8 | B11: Ensure auditing is configured for Docker files and directories - containerd.sock | C11: Audit containerd.sock, if applicable. | D11: ORCH-2-8; DOCK-2-2
A12: 1.1.9 | B12: Ensure auditing is configured for Docker files and directories - docker.sock | C12: Audit docker.sock, if applicable. | D12: ORCH-2-8; DOCK-2-2
A13: 1.1.10 | B13: Ensure auditing is configured for Docker files and directories - /etc/default/docker | C13: Audit /etc/default/docker, if applicable. | D13: ORCH-2-8; DOCK-2-2
A14: 1.1.11 | B14: Ensure auditing is configured for Docker files and directories - /etc/docker/daemon.json | C14: Audit /etc/docker/daemon.json, if applicable. | D14: ORCH-2-8; DOCK-2-2
A15: 1.1.12 | B15: Ensure auditing is configured for Docker files and directories - /etc/containerd/config.toml | C15: Audit /etc/containerd/config.toml if applicable. | D15: ORCH-2-8; DOCK-2-2
... A21: 1.1.18 | B21: Ensure auditing is configured for Docker files and directories - /usr/bin/runc | C21: Audit /usr/bin/runc if applicable. | D21: ORCH-2-8; DOCK-2-2
A22: General Configuration
A23: 1.2.1 | B23: Ensure the container host has been Hardened | C23: A container host is able to run one or more containers. It is of utmost importance to harden the host to mitigate host security misconfiguration. | D23: NODES-1-1; NODES-1-2; NODES-1-3; NODES-1-6; NODES-1-7; NODES-2-1; NODES-2-2; NODES-2-3; NODES-2-4; NODES-2-5; NODES-2-7; NODES-2-8; NODES-2-11; NODES-2-12; NODES-3-1; NODES-3-2; NODES-3-3; NODES-3-4; NODES-3-6; NODES-3-7; NODES-4-1; NODES-4-3
A24: 1.2.2 | B24: Ensure that the version of Docker is up to date | C24: Frequent releases for Docker are issued which address security vulnerabilities, resolve product bugs and bring in new functionality. You should keep a tab on these product updates and upgrade as frequently as possible in line with the general IT security policy of your organization. | D24: ORCH-2-2; ORCH-2-7; ORCH-2-12; DOCK-2-6; DOCK-2-9
A25: Docker Daemon Configuration
A26: 2.1 | B26: Run the Docker daemon as a non-root user, if possible | C26: Rootless mode executes the Docker daemon and containers inside a user namespace, with both the daemon and the container are running without root privileges. | D26: DOCK-3-7
A27: 2.2 | B27: Ensure network traffic is restricted between containers on the default bridge | C27: By default, all network traffic is allowed between containers on the same host on the default network bridge. If not desired, restrict all inter-container communication. Link specific containers together that require communication. Alternatively, you can create custom network and only join containers that need to communicate to that custom network. | D27: DOCK-4-4
A28: 2.3 | B28: Ensure the logging level is set to 'info' | C28: Set Docker daemon log level to info. | D28: DOCK-1-1
A29: 2.4 | B29: Ensure Docker is allowed to make changes to iptables | C29: The iptables firewall is used to set up, maintain, and inspect the tables of IP packet filter rules within the Linux kernel. The Docker daemon should be allowed to make changes to the iptables ruleset. | D29: DOCK-1-3
A30: 2.5 | B30: Ensure insecure registries are not used | C30: Docker considers a private registry either secure or insecure. By default, registries are considered secure. | D30: -
A31: 2.6 | B31: Ensure aufs storage driver is not used | C31: Do not use aufs as the storage driver for your Docker instance. | D31: DOCK-1-5
A32: 2.7 | B32: Ensure TLS authentication for Docker daemon is configured | C32: It is possible to make the Docker daemon available remotely over a TCP port. If this is required, you should ensure that TLS authentication is configured in order to restrict access to the Docker daemon via IP address and port. | D32: DOCK-3-5; DOCK-3-6
A33: 2.8 | B33: Ensure the default ulimit is configured appropriately | C33: Set the default ulimit options as appropriate in your environment. | D33: DOCK-2-3
A34: 2.9 | B34: Enable user namespace support | C34: You should enable user namespace support in Docker daemon to utilize container user to host user re-mapping. This recommendation is beneficial where the containers you are using do not have an explicit container user defined in the container image. If the container images that you are using have a pre-defined non-root user, this recommendation may be skipped as this feature is still in its infancy, and might result in unpredictable issues or difficulty in configuration. | D34: -
A35: 2.10 | B35: Ensure the default cgroup usage has been confirmed | C35: The --cgroup-parent option allows you to set the default cgroup parent to use for all containers. If there is no specific usage requirement for this, the setting should be left at its default. | D35: DOCK-1-6; DOCK-4-5
A36: 2.11 | B36: Ensure base device size is not changed until needed | C36: Under certain circumstances, you might need containers larger than 10G. Where this applies you should carefully choose the base device size. | D36: -
A37: 2.12 | B37: Ensure that authorization for Docker client commands is enabled | C37: You should use native Docker authorization plugins or a third party authorization mechanism with the Docker daemon to manage access to Docker client commands. | D37: ORCH-2-10; DOCK-4-3
... A43: 2.18 | B43: Ensure that experimental features are not implemented in production | C43: Experimental features should not be enabled in production. | D43: DOCK-1-4
A44: Docker Daemon Configuration Files
A45: 3.1 | B45: Ensure that the docker.service file ownership is set to root:root | C45: You should verify that the docker.service file ownership and group ownership are correctly set to root. | D45: ORCH-2-5; ORCH-2-6; DOCK-2-5
A46: 3.2 | B46: Ensure that docker.service file permissions are appropriately set | C46: You should verify that the docker.service file permissions are either set to 644 or to a more restrictive value. | D46: ORCH-2-5; ORCH-2-6; DOCK-2-5
A47: 3.3 | B47: Ensure that docker.socket file ownership is set to root:root | C47: You should verify that the docker.socket file ownership and group ownership are correctly set to root. | D47: ORCH-2-5; ORCH-2-6; DOCK-2-5
A48: 3.4 | B48: Ensure that docker.socket file permissions are set to 644 or more restrictive | C48: You should verify that the file permissions on the docker.socket file are correctly set to 644 or more restrictively. | D48: ORCH-2-5; ORCH-2-6; DOCK-2-5
A49: 3.5 | B49: Ensure that the /etc/docker directory ownership is set to root:root | C49: You should verify that the /etc/docker directory ownership and group ownership is correctly set to root. | D49: ORCH-2-5; ORCH-2-6; DOCK-2-5
A50: 3.6 | B50: Ensure that /etc/docker directory permissions are set to 755 or more restrictively | C50: You should verify that the /etc/docker directory permissions are correctly set to 755 or more restrictively. | D50: ORCH-2-5; ORCH-2-6; DOCK-2-5
A51: 3.7 | B51: Ensure that registry certificate file ownership is set to root:root | C51: You should verify that all the registry certificate files (usually found under /etc/docker/certs.d/<registry-name> directory) are individually owned and group owned by root. | D51: ORCH-2-5; ORCH-2-6; DOCK-2-5
A52: 3.8 | B52: Ensure that registry certificate file permissions are set to 444 or more restrictively | C52: You should verify that all the registry certificate files (usually found under /etc/docker/certs.d/<registry-name> directory) have permissions of 444 or are set more restrictively. | D52: ORCH-2-5; ORCH-2-6; DOCK-2-5
A53: 3.9 | B53: Ensure that TLS CA certificate file ownership is set to root:root | C53: You should verify that the TLS CA certificate file (the file that is passed along with the --tlscacert parameter) is individually owned and group owned by root. | D53: ORCH-2-5; ORCH-2-6; DOCK-2-5
A54: 3.10 | B54: Ensure that TLS CA certificate file permissions are set to 444 or more restrictively | C54: You should verify that the TLS CA certificate file (the file that is passed along with the --tlscacert parameter) has permissions of 444 or is set more restrictively. | D54: ORCH-2-5; ORCH-2-6; DOCK-2-5
A55: 3.11 | B55: Ensure that Docker server certificate file ownership is set to root:root | C55: You should verify that the Docker server certificate file (the file that is passed along with the --tlscert parameter) is individual owned and group owned by root. | D55: ORCH-2-5; ORCH-2-6; DOCK-2-5
A56: 3.12 | B56: Ensure that the Docker server certificate file permissions are set to 444 or more restrictively | C56: You should verify that the Docker server certificate file (the file that is passed along with the --tlscert parameter) has permissions of 444 or more restrictive permissions. | D56: ORCH-2-5; ORCH-2-6; DOCK-2-5
... A68: 3.24 | B68: Ensure that the Containerd socket file permissions are set to 660 or more restrictively | C68: You should verify that the Containerd socket file has permissions of 660 or are configured more restrictively. | D68: ORCH-2-5; ORCH-2-6; DOCK-2-5
A69: Container Images and Build File Configuration
A70: 4.1 | B70: Ensure that a user for the container has been created | C70: Containers should run as a non-root user. | D70: MAN-3-2
A71: 4.2 | B71: Ensure that containers use only trusted base images | C71: You should ensure that container images you use are either written from scratch or are based on another established and trusted base image downloaded over a secure channel. | D71: IMG-1-2
A72: 4.3 | B72: Ensure that unnecessary packages are not installed in the container | C72: Containers should have as small a footprint as possible, and should not contain unnecessary software packages which could increase their attack surface. | D72: IMG-1-4; IMG-4-1
A73: 4.4 | B73: Ensure images are scanned and rebuilt to include security patches | C73: Images should be scanned frequently for any vulnerabilities. You should rebuild all images to include these patches and then instantiate new containers from them. | D73: IMG-1-3; IMG-1-5; IMG-2-1; IMG-2-2; IMG-3-2; IMG-3-4
A74: 4.5 | B74: Ensure Content trust for Docker is Enabled | C74: Content trust is disabled by default and should be enabled in line with organizational security policy. | D74: IMG-3-3
A75: 4.6 | B75: Ensure that HEALTHCHECK instructions have been added to container images | C75: You should add the HEALTHCHECK instruction to your Docker container images in order to ensure that health checks are executed against running containers. | D75: MAN-2-1
A76: 4.7 | B76: Ensure update instructions are not used alone in Dockerfiles | C76: You should not use OS package manager update instructions such as apt-get updateor yum update either alone or in a single line in any Dockerfiles used to generate images under review. | D76: IMG-1-4; IMG-3-2
A77: 4.8 | B77: Ensure setuid and setgid permissions are removed | C77: Removing setuid and setgid permissions in the images can prevent privilege escalation attacks within containers. | D77: IMG-4-1
A78: 4.9 | B78: Ensure that COPY is used instead of ADD in Dockerfiles | C78: You should use the COPY instruction instead of the ADD instruction in the Dockerfile. | D78: IMG-1-4
A79: 4.10 | B79: Ensure secrets are not stored in Dockerfiles | C79: Do not store any secrets in Dockerfiles. | D79: IMG-1-1; MAN-1-1
A80: 4.11 | B80: Ensure only verified packages are installed | C80: You should verify the authenticity of packages before installing them into images. | D80: IMG-1-4; IMG-2-1
A81: 4.12 | B81: Ensure all signed artifacts are validated | C81: Validate artifacts signatures before uploading to the package registry. | D81: IMG-3-3
A82: Container Runtime Configuration
A83: 5.1 | B83: Ensure swarm mode is not Enabled, if not needed | C83: Do not enable swarm mode on a Docker engine instance unless this is needed. | D83: -
A84: 5.2 | B84: Ensure that, if applicable, an AppArmor Profile is enabled | C84: AppArmor is an effective and easy-to-use Linux application security system. It is available on some Linux distributions by default, for example, on Debian and Ubuntu. | D84: MAN-4-1
A85: 5.3 | B85: Ensure that, if applicable, SELinux security options are set | C85: SELinux is an effective and easy-to-use Linux application security system. It is available by default on some distributions such as Red Hat and Fedora. | D85: -
A86: 5.4 | B86: Ensure that Linux kernel capabilities are restricted within containers | C86: By default, Docker starts containers with a restricted set of Linux kernel capabilities. This means that any process can be granted the required capabilities instead of giving it root access. Using Linux kernel capabilities, processes in general do not need to run as the root user. | D86: MAN-3-4
A87: 5.5 | B87: Ensure that privileged containers are not used | C87: Using the --privileged flag provides all Linux kernel capabilities to the container to which it is applied and therefore overwrites the --cap-add and --cap-drop flags. For this reason you should ensure that it is not used. | D87: MAN-1-2; MAN-1-4; MAN-3-2
A88: 5.6 | B88: Ensure sensitive host system directories are not mounted on containers | C88: You should not allow sensitive host system directories such as those listed below to be mounted as container volumes, especially in read-write mode. / /boot /dev /etc /lib /lib64 /proc /sys /usr | D88: MAN-2-2; MAN-2-4
A89: 5.7 | B89: Ensure sshd is not run within containers | C89: The SSH daemon should not be running within the container. You should SSH into the Docker host, and use docker exec to enter a container. | D89: CONT-1-3
A90: 5.8 | B90: Ensure privileged ports are not mapped within containers | C90: The TCP/IP port numbers below 1024 are considered privileged ports. Normal users and processes are not allowed to use them for various security reasons. Docker does, however allow a container port to be mapped to a privileged port. | D90: -
A91: 5.9 | B91: Ensure that only needed ports are open on the container | C91: The dockerfile for a container image defines the ports which are opened by default on a container instance. The list of ports are relevant to the application you are running within the container and should only be open if they are needed. | D91: -
A92: 5.10 | B92: Ensure that the host's network namespace is not shared | C92: When the networking mode on a container is set to --net=host, the container is not placed inside a separate network stack. Effectively, applying this option instructs Docker to not containerize the container's networking. The consequence of this is that the container lives "outside" in the main Docker host and has full access to its network interfaces. | D92: DOCK-4-4; MAN-1-3
A93: 5.11 | B93: Ensure that the memory usage for containers is limited | C93: By default, all containers on a Docker host share resources equally. By using the resource management capabilities of the Docker host, you can control the amount of memory that a container is able to use. | D93: MAN-2-8; CONT-1-2
A94: 5.12 | B94: Ensure that CPU priority is set appropriately on containers | C94: By default, all containers on a Docker host share resources equally. By using the resource management capabilities of the Docker host you can control the host CPU resources that a container may consume. | D94: MAN-2-8; CONT-1-2
... A114: 5.32 | B114: Ensure that the Docker socket is not mounted inside any containers | C114: The Docker socket docker.sock should not be mounted inside a container. | D114: -
A115: Docker Security Operations
A116: 6.1 | B116: Ensure that image sprawl is avoided | C116: You should not keep a large number of container images on the same host. Use only tagged images as appropriate. | D116: DOCK-2-8
A117: 6.2 | B117: Ensure that container sprawl is avoided | C117: You should not keep a large number of containers on the same host. | D117: ORCH-3-5; DOCK-3-4
A118: Docker Swarm Configuration
A119: 7.1 | B119: Ensure that the minimum number of manager nodes have been created in a swarm | C119: You should ensure that the minimum number of required manager nodes is created in a swarm. | D119: DOCK-1-8
A120: 7.2 | B120: Ensure that swarm services are bound to a specific host interface | C120: By default, Docker swarm services will listen on all interfaces on the host. This may not be necessary for the operation of the swarm where the host has multiple network interfaces. | D120: DOCK-2-13
A121: 7.3 | B121: Ensure that all Docker swarm overlay networks are encrypted | C121: Ensure that all Docker swarm overlay networks are encrypted. | D121: ORCH-1-5; DOCK-2-14
A122: 7.4 | B122: Ensure that Docker's secret management commands are used for managing secrets in a swarm cluster | C122: You should use Docker's in-built secret management command for control of secrets. | D122: ORCH-3-6; DOCK-3-8
A123: 7.5 | B123: Ensure that swarm manager is run in auto-lock mode | C123: You should review whether you wish to run Docker swarm manager in auto-lock mode. | D123: DOCK-4-6
A124: 7.6 | B124: Ensure that the swarm manager auto-lock key is rotated periodically | C124: You should rotate the swarm manager auto-lock key periodically. | D124: DOCK-4-7
A125: 7.7 | B125: Ensure that node certificates are rotated as appropriate | C125: You should rotate swarm node certificates in line with your organizational security policy. | D125: DOCK-2-15
A126: 7.8 | B126: Ensure that CA certificates are rotated as appropriate | C126: You should rotate root CA certificates as appropriate. | D126: DOCK-3-9
A127: 7.9 | B127: Ensure that management plane traffic is separated from data plane traffic | C127: You should separate management plane traffic from data plane traffic. | D127: DOCK-2-12

Sheet CIS Kubernetes
A1: ID в CIS k8s | B1: Требование | C1: Примечание | D1: JCSF
A2: Control Plane Components
A3: Control Plane Node Configuration Files
A4: 1.1.1 | B4: Ensure that the API server pod specification file permissions are set to 600 or more restrictive | C4: Ensure that the API server pod specification file has permissions of 600 or more restrictive. | D4: ORCH-2-5
A5: 1.1.2 | B5: Ensure that the API server pod specification file ownership is set to root:root | C5: Ensure that the API server pod specification file ownership is set to root:root. | D5: ORCH-2-5
A6: 1.1.3 | B6: Ensure that the controller manager pod specification file permissions are set to 600 or more restrictive | C6: Ensure that the controller manager pod specification file has permissions of 600 or more restrictive. | D6: ORCH-2-5
A7: 1.1.4 | B7: Ensure that the controller manager pod specification file ownership is set to root:root | C7: Ensure that the controller manager pod specification file ownership is set to root:root. | D7: ORCH-2-5
A8: 1.1.5 | B8: Ensure that the scheduler pod specification file permissions are set to 600 or more restrictive | C8: Ensure that the scheduler pod specification file has permissions of 600 or more restrictive. | D8: ORCH-2-5
A9: 1.1.6 | B9: Ensure that the scheduler pod specification file ownership is set to root:root | C9: Ensure that the scheduler pod specification file ownership is set to root:root. | D9: ORCH-2-5
A10: 1.1.7 | B10: Ensure that the etcd pod specification file permissions are set to 600 or more restrictive | C10: Ensure that the /etc/kubernetes/manifests/etcd.yaml file has permissions of 600 or more restrictive. | D10: ORCH-2-5
A11: 1.1.8 | B11: Ensure that the etcd pod specification file ownership is set to root:root | C11: Ensure that the /etc/kubernetes/manifests/etcd.yaml file ownership is set to root:root. | D11: ORCH-2-5
A12: 1.1.9 | B12: Ensure that the Container Network Interface file permissions are set to 600 or more restrictive | C12: Ensure that the Container Network Interface files have permissions of 600 or more restrictive. | D12: ORCH-2-5
A13: 1.1.10 | B13: Ensure that the Container Network Interface file ownership is set to root:root | C13: Ensure that the Container Network Interface files have ownership set to root:root. | D13: ORCH-2-5
A14: 1.1.11 | B14: Ensure that the etcd data directory permissions are set to 700 or more restrictive | C14: Ensure that the etcd data directory has permissions of 700 or more restrictive. | D14: ORCH-2-5
A15: 1.1.12 | B15: Ensure that the etcd data directory ownership is set to etcd:etcd | C15: Ensure that the etcd data directory ownership is set to etcd:etcd. | D15: ORCH-2-5
... A24: 1.1.21 | B24: Ensure that the Kubernetes PKI key file permissions are set to 600 | C24: Ensure that Kubernetes PKI key files have permissions of 600. | D24: ORCH-2-5
A25: API Server
A26: 1.2.1 | B26: Ensure that the --anonymous-auth argument is set to false | C26: Disable anonymous requests to the API server. | D26: ORCH-1-1
A27: 1.2.2 | B27: Ensure that the --token-auth-file parameter is not set | C27: Do not use token based authentication. | D27: ORCH-1-2
A28: 1.2.3 | B28: Ensure that the DenyServiceExternalIPs is set | C28: This admission controller rejects all net-new usage of the Service field externalIPs. | D28: -
A29: 1.2.4 | B29: Ensure that the --kubelet-client-certificate and --kubelet client-key arguments are set as appropriate | C29: Enable certificate based kubelet authentication. | D29: ORCH-1-5
A30: 1.2.5 | B30: Ensure that the --kubelet-certificate-authority argument is set as appropriate | C30: Verify kubelet's certificate before establishing connection. | D30: ORCH-1-5
A31: 1.2.6 | B31: Ensure that the --authorization-mode argument is not set to AlwaysAllow | C31: Do not always authorize all requests. | D31: ORCH-1-1
A32: 1.2.7 | B32: Ensure that the --authorization-mode argument includes Node | C32: Restrict kubelet nodes to reading only objects associated with them. | D32: ORCH-1-1
A33: 1.2.8 | B33: Ensure that the --authorization-mode argument includes RBAC | C33: Turn on Role Based Access Control. | D33: ORCH-1-1; ORCH-2-10
A34: 1.2.9 | B34: Ensure that the admission control plugin EventRateLimit is set | C34: Limit the rate at which the API server accepts requests. | D34: -
A35: 1.2.10 | B35: Ensure that the admission control plugin AlwaysAdmit is not set | C35: Do not allow all requests. | D35: ORCH-1-6
A36: 1.2.11 | B36: Ensure that the admission control plugin AlwaysPullImages is set | C36: Always pull images. | D36: ORCH-2-4
A37: 1.2.12 | B37: Ensure that the admission control plugin ServiceAccount is set | C37: Automate service accounts management. | D37: -
... A55: 1.2.30 | B55: Ensure that the --service-account-extend-token-expiration parameter is set to false | C55: By default Kubernetes extends service account token lifetimes to one year to aid in transition from the legacy token settings. | D55: -
A56: Controller Manager
A57: 1.3.1 | B57: Ensure that the --terminated-pod-gc-threshold argument is set as appropriate | C57: Activate garbage collector on pod termination, as appropriate. | D57: -
A58: 1.3.2 | B58: Ensure that the --profiling argument is set to false | C58: Disable profiling, if not needed. | D58: -
A59: 1.3.3 | B59: Ensure that the --use-service-account-credentials argument is set to true | C59: Use individual service account credentials for each controller. | D59: -
A60: 1.3.4 | B60: Ensure that the --service-account-private-key-file argument is set as appropriate | C60: Explicitly set a service account private key file for service accounts on the controller manager. | D60: -
A61: 1.3.5 | B61: Ensure that the --root-ca-file argument is set as appropriate | C61: Allow pods to verify the API server's serving certificate before establishing connections. | D61: -
A62: 1.3.6 | B62: Ensure that the RotateKubeletServerCertificate argument is set to true | C62: Enable kubelet server certificate rotation on controller-manager. | D62: -
A63: 1.3.7 | B63: Ensure that the --bind-address argument is set to 127.0.0.1 | C63: Do not bind the Controller Manager service to non-loopback insecure addresses. | D63: -
A64: Scheduler
A65: 1.4.1 | B65: Ensure that the --profiling argument is set to false | C65: Disable profiling, if not needed. | D65: -
A66: 1.4.2 | B66: Ensure that the --bind-address argument is set to 127.0.0.1 | C66: Do not bind the scheduler service to non-loopback insecure addresses. | D66: -
A67: Etcd
A68: 2.1 | B68: Ensure that the --cert-file and --key-file arguments are set as appropriate | C68: Configure TLS encryption for the etcd service. | D68: ORCH-3-4
A69: 2.2 | B69: Ensure that the --cert-file and --key-file arguments are set as appropriate | C69: Configure TLS encryption for the etcd service. | D69: ORCH-3-4
A70: 2.3 | B70: Ensure that the --client-cert-auth argument is set to true | C70: Enable client authentication on etcd service. | D70: ORCH-3-4
A71: 2.4 | B71: Ensure that the --auto-tls argument is not set to true | C71: Do not use self-signed certificates for TLS. | D71: ORCH-3-4
A72: 2.5 | B72: Ensure that the --peer-cert-file and --peer-key-file arguments are set as appropriate | C72: etcd should be configured to make use of TLS encryption for peer connections. | D72: ORCH-3-4
A73: 2.6 | B73: Ensure that the --peer-client-cert-auth argument is set to true | C73: etcd should be configured for peer authentication. | D73: ORCH-3-4
A74: 2.7 | B74: Ensure that the --peer-auto-tls argument is not set to true | C74: Do not use automatically generated self-signed certificates for TLS connections between peers. | D74: ORCH-3-4
A75: 2.8 | B75: Ensure that a unique Certificate Authority is used for etcd | C75: Use a different certificate authority for etcd from the one used for Kubernetes. | D75: ORCH-3-4
A76: Control Plane Configuration
A77: Authentication and Authorization
A78: 3.1.1 | B78: Client certificate authentication should not be used for users | C78: Kubernetes provides the option to use client certificates for user authentication. However as there is no way to revoke these certificates when a user leaves an organization or loses their credential, they are not suitable for this purpose. It is not possible to fully disable client certificate use within a cluster as it is used for component to component authentication. | D78: ORCH-2-11
A79: 3.1.2 | B79: Service account token authentication should not be used for users | C79: Kubernetes provides service account tokens which are intended for use by workloads running in the Kubernetes cluster, for authentication to the API server. These tokens are not designed for use by end-users and do not provide for features such as revocation or expiry, making them insecure. A newer version of the feature (Bound service account token volumes) does introduce expiry but still does not allow for specific revocation. | D79: ORCH-1-3; ORCH-2-11
A80: 3.1.3 | B80: Bootstrap token authentication should not be used for users | C80: Kubernetes provides bootstrap tokens which are intended for use by new nodes joining the cluster. These tokens are not designed for use by end-users they are specifically designed for the purpose of bootstrapping new nodes and not for general authentication. | D80: ORCH-1-3; ORCH-2-11
A81: Logging
A82: 3.2.1 | B82: Ensure that a minimal audit policy is created | C82: Kubernetes can audit the details of requests made to the API server. The --audit policy-file flag must be set for this logging to be enabled. | D82: ORCH-2-8
A83: 3.2.2 | B83: Ensure that the audit policy covers key security concerns | C83: Ensure that the audit policy created for the cluster covers key security concerns. | D83: ORCH-2-9; CONT-2-3; CONT-3-3
A84: Worker Nodes
A85: Worker Node Configuration Files
A86: 4.1.1 | B86: Ensure that the kubelet service file permissions are set to 600 or more restrictive | C86: Ensure that the kubelet service file has permissions of 600 or more restrictive. | D86: ORCH-2-6
A87: 4.1.2 | B87: Ensure that the kubelet service file ownership is set to root:root | C87: Ensure that the kubelet service file ownership is set to root:root. | D87: ORCH-2-6
A88: 4.1.3 | B88: If proxy kubeconfig file exists ensure permissions are set to 600 or more restrictive | C88: If kube-proxy is running, and if it is using a file-based kubeconfig file, ensure that the proxy kubeconfig file has permissions of 600 or more restrictive. | D88: ORCH-2-6
A89: 4.1.4 | B89: If proxy kubeconfig file exists ensure ownership is set to root:root | C89: If kube-proxy is running, ensure that the file ownership of its kubeconfig file is set to root:root. | D89: ORCH-2-6
A90: 4.1.5 | B90: Ensure that the --kubeconfig kubelet.conf file permissions are set to 600 or more restrictive | C90: Ensure that the kubelet.conf file has permissions of 600 or more restrictive. | D90: ORCH-2-6
A91: 4.1.6 | B91: Ensure that the --kubeconfig kubelet.conf file ownership is set to root:root | C91: Ensure that the kubelet.conf file ownership is set to root:root. | D91: ORCH-2-6
A92: 4.1.7 | B92: Ensure that the certificate authorities file permissions are set to 644 or more restrictive | C92: Ensure that the certificate authorities file has permissions of 644 or more restrictive. | D92: ORCH-2-6
A93: 4.1.8 | B93: Ensure that the client certificate authorities file ownership is set to root:root | C93: Ensure that the certificate authorities file ownership is set to root:root. | D93: ORCH-2-6
A94: 4.1.9 | B94: If the kubelet config.yaml configuration file is being used validate permissions set to 600 or more restrictive | C94: Ensure that if the kubelet refers to a configuration file with the --config argument, that file has permissions of 600 or more restrictive. | D94: ORCH-2-6
A95: 4.1.10 | B95: If the kubelet config.yaml configuration file is being used validate file ownership is set to root:root | C95: Ensure that if the kubelet refers to a configuration file with the --config argument, that file is owned by root:root. | D95: ORCH-2-6
A96: Kubelet
A97: 4.2.1 | B97: Ensure that the --anonymous-auth argument is set to false | C97: Disable anonymous requests to the Kubelet server. | D97: ORCH-1-8
A98: 4.2.2 | B98: Ensure that the --authorization-mode argument is not set to AlwaysAllow | C98: Do not allow all requests. Enable explicit authorization. | D98: ORCH-1-8; ORCH-1-11
A99: 4.2.3 | B99: Ensure that the --client-ca-file argument is set as appropriate | C99: Enable Kubelet authentication using certificates. | D99: ORCH-1-5; ORCH-1-10
A100: 4.2.4 | B100: Verify that if defined, readOnlyPort is set to 0 | C100: Disable the read-only port. | D100: ORCH-1-9
A101: 4.2.5 | B101: Ensure that the --streaming-connection-idle-timeout argument is not set to 0 | C101: Do not disable timeouts on streaming connections. | D101: -
A102: 4.2.6 | B102: Ensure that the --make-iptables-util-chains argument is set to true | C102: Allow Kubelet to manage iptables. | D102: -
A103: 4.2.7 | B103: Ensure that the --hostname-override argument is not set | C103: Do not override node hostnames. | D103: -
A104: 4.2.8 | B104: Ensure that the eventRecordQPS argument is set to a level which ensures appropriate event capture | C104: Security relevant information should be captured. The eventRecordQPS on the Kubelet configuration can be used to limit the rate at which events are gathered and sets the maximum event creations per second. Setting this too low could result in relevant events not being logged, however the unlimited setting of 0 could result in a denial of service on the kubelet. | D104: -
A105: 4.2.9 | B105: Ensure that the --tls-cert-file and --tls-private-key-file arguments are set as appropriate | C105: Setup TLS connection on the Kubelets. | D105: ORCH-1-10
A106: 4.2.10 | B106: Ensure that the --rotate-certificates argument is not set to false | C106: Enable kubelet client certificate rotation. | D106: ORCH-3-3
A107: 4.2.11 | B107: Verify that the RotateKubeletServerCertificate argument is set to true | C107: Enable kubelet server certificate rotation. | D107: ORCH-3-3
A108: 4.2.12 | B108: Ensure that the Kubelet only makes use of Strong Cryptographic Ciphers | C108: Ensure that the Kubelet is configured to only use strong cryptographic ciphers. | D108: ORCH-1-10
... A111: 4.2.15 | B111: Ensure that the --IPAddressDeny is set to any | C111: Ensuring that --IPAddressDeny is set to "Any" will facilitate allowlisting of only IP addresses that are explicitly set with the --IPAddressAllow parameter which will block unspecified IP addresses from communicating with the kubelet component. | D111: -
A112: Kube-proxy
A113: 4.3.1 | B113: Ensure that the kube-proxy metrics service is bound to localhost | C113: Do not bind the kube-proxy metrics port to non-loopback addresses. | D113: -
A114: Policies
A115: RBAC and Service Accounts
A116: 5.1.1 | B116: Ensure that the cluster-admin role is only used where required | C116: The RBAC role cluster-admin provides wide-ranging powers over the environment and should be used only where and when needed. | D116: ORCH-2-1; ORCH-2-3; ORCH-2-10
A117: 5.1.2 | B117: Minimize access to secrets | C117: The Kubernetes API stores secrets, which may be service account tokens for the Kubernetes API or credentials used by workloads in the cluster. Access to these secrets should be restricted to the smallest possible group of users to reduce the risk of privilege escalation. | D117: ORCH-2-10; MAN-1-1
A118: 5.1.3 | B118: Minimize wildcard use in Roles and ClusterRoles | C118: Kubernetes Roles and ClusterRoles provide access to resources based on sets of objects and actions that can be taken on those objects. It is possible to set either of these to be the wildcard "*" which matches all items. Use of wildcards is not optimal from a security perspective as it may allow for inadvertent access to be granted when new resources are added to the Kubernetes API either as CRDs or in later versions of the product. | D118: ORCH-2-10
A119: 5.1.4 | B119: Minimize access to create pods | C119: The ability to create pods in a namespace can provide a number of opportunities for privilege escalation, such as assigning privileged service accounts to these pods or mounting hostPaths with access to sensitive data (unless Pod Security Policies are implemented to restrict this access). As such, access to create new pods should be restricted to the smallest possible group of users. | D119: ORCH-2-10
A120: 5.1.5 | B120: Ensure that default service accounts are not actively used | C120: The default service account should not be used to ensure that rights granted to applications can be more easily audited and reviewed. | D120: ORCH-2-10
A121: 5.1.6 | B121: Ensure that Service Account Tokens are only mounted where necessary | C121: Service accounts tokens should not be mounted in pods except where the workload running in the pod explicitly needs to communicate with the API server. | D121: ORCH-2-10
A122: 5.1.7 | B122: Avoid use of system:masters group | C122: The special group system:masters should not be used to grant permissions to any user or service account, except where strictly necessary (e.g. bootstrapping access prior to RBAC being fully available). | D122: ORCH-2-10
A123: 5.1.8 | B123: Limit use of the Bind, Impersonate and Escalate permissions in the Kubernetes cluster | C123: Cluster roles and roles with the impersonate, bind or escalate permissions should not be granted unless strictly required. Each of these permissions allow a particular subject to escalate their privileges beyond those explicitly granted by cluster administrators. | D123: ORCH-2-10
A124: 5.1.9 | B124: Minimize access to create persistent volumes | C124: The ability to create persistent volumes in a cluster can provide an opportunity for privilege escalation, via the creation of hostPath volumes. As persistent volumes are not covered by Pod Security Admission, a user with access to create persistent volumes may be able to get access to sensitive files from the underlying host even where restrictive Pod Security Admission policies are in place. | D124: ORCH-2-10
A125: 5.1.10 | B125: Minimize access to the proxy sub-resource of nodes | C125: Users with access to the Proxy sub-resource of Node objects automatically have permissions to use the kubelet API, which may allow for privilege escalation or bypass cluster security controls such as audit logs. The kubelet provides an API which includes rights to execute commands in any container running on the node. Access to this API is covered by permissions to the main Kubernetes API via the node object. The proxy sub-resource specifically allows wide ranging access to the kubelet API. Direct access to the kubelet API bypasses controls like audit logging (there is no audit log of kubelet API access) and admission control. | D125: ORCH-2-10
A126: 5.1.11 | B126: Minimize access to the approval sub-resource of certificatesigningrequests objects | C126: Users with access to the update the approval sub-resource of CertificateSigningRequests objects can approve new client certificates for the Kubernetes API effectively allowing them to create new high-privileged user accounts. This can allow for privilege escalation to full cluster administrator, depending on users configured in the cluster. | D126: ORCH-2-10
A127: 5.1.12 | B127: Minimize access to webhook configuration objects | C127: Users with rights to create/modify/delete validatingwebhookconfigurations or mutatingwebhookconfigurations can control webhooks that can read any object admitted to the cluster, and in the case of mutating webhooks, also mutate admitted objects. This could allow for privilege escalation or disruption of the operation of the cluster. | D127: ORCH-2-10
...

Sheet CIS Linux (Debian)
A1: ID в CIS k8s | B1: Требование | C1: Примечание | D1: JCSF
A2: Initial Setup
A3: Filesystem
A4: Configure Filesystem Kernel Modules
A5: 1.1.1.1 | B5: Ensure cramfs kernel module is not available | C5: Removing support for unneeded filesystem types reduces the local attack surface of the system. If this filesystem type is not needed, disable it | D5: -
A6: 1.1.1.2 | B6: Ensure freevxfs kernel module is not available | C6: Removing support for unneeded filesystem types reduces the local attack surface of the system. If this filesystem type is not needed, disable it | D6: -
A7: 1.1.1.3 | B7: Ensure hfs kernel module is not available | C7: Removing support for unneeded filesystem types reduces the local attack surface of the system. If this filesystem type is not needed, disable it | D7: -
A8: 1.1.1.4 | B8: Ensure hfsplus kernel module is not available | C8: Removing support for unneeded filesystem types reduces the local attack surface of the system. If this filesystem type is not needed, disable it | D8: -
A9: 1.1.1.5 | B9: Ensure jffs2 kernel module is not available | C9: Removing support for unneeded filesystem types reduces the local attack surface of the system. If this filesystem type is not needed, disable it | D9: -
A10: 1.1.1.6 | B10: Ensure overlay kernel module is not available | C10: Disabling the overlay kernel module reduces the local attack surface by removing support for unnecessary filesystem types and mitigates potential risks associated with unauthorized execution of setuid files, enhancing the overall system security | D10: -
A11: 1.1.1.7 | B11: Ensure squashfs kernel module is not available | C11: Removing support for unneeded filesystem types reduces the local attack surface of the system. If this filesystem type is not needed, disable it | D11: -
A12: 1.1.1.8 | B12: Ensure udf kernel module is not available | C12: Removing support for unneeded filesystem types reduces the local attack surface of the system. If this filesystem type is not needed, disable it | D12: -
A13: 1.1.1.9 | B13: Ensure firewire-core kernel module is not available | C13: Disabling FireWire protects the system against exploitation of any flaws in its implementation | D13: -
A14: 1.1.1.10 | B14: Ensure usb-storage kernel module is not available | C14: Restricting USB access on the system will decrease the physical attack surface for a device and diminish the possible vectors to introduce malware | D14: -
A15: 1.1.1.11 | B15: Ensure unused filesystems kernel modules are not available | C15: Removing support for unneeded filesystem types reduces the local attack surface of the system. If this filesystem type is not needed, disable it | D15: -
A16: Configure Filesystem Partitions
A17: Configure /tmp
A18: 1.1.2.1.1 | B18: Ensure /tmp is tmpfs or a separate partition | C18: Making /tmp its own file system allows an administrator to set additional mount options such as the noexec option on the mount, making /tmp useless for an attacker to install executable code. It would also prevent an attacker from establishing a hard link to a system setuid program and wait for it to be updated. Once the program was updated, the hard link would be broken, and the attacker would have his own copy of the program | D18: -
A19: 1.1.2.1.2 | B19: Ensure nodev option set on /tmp partition | C19: Since the /tmp filesystem is not intended to support devices, set this option to ensure that users cannot create a block or character special devices in /tmp | D19: -
A20: 1.1.2.1.3 | B20: Ensure nosuid option set on /tmp partition | C20: Since the /tmp filesystem is only intended for temporary file storage, set this option to ensure that users cannot create setuid files in /tmp | D20: -
A21: 1.1.2.1.4 | B21: Ensure noexec option set on /tmp partition | C21: Since the /tmp filesystem is only intended for temporary file storage, set this option to ensure that users cannot run executable binaries from /tmp | D21: -
A22: Configure /dev/shm
A23: 1.1.2.2.1 | B23: Ensure /dev/shm is tmpfs or a separate partition | C23: Making /dev/shm its own file system allows an administrator to set additional mount options such as the noexec option on the mount, making /dev/shm useless for an attacker to install executable code. It would also prevent an attacker from establishing a hard link to a system setuid program and wait for it to be updated. Once the program was updated, the hard link would be broken and the attacker would have his own copy of the program | D23: -
A24: 1.1.2.2.2 | B24: Ensure nodev option set on /dev/shm partition | C24: Since the /dev/shm filesystem is not intended to support devices, set this option to ensure that users cannot attempt to create special devices in /dev/shm partitions | D24: -
A25: 1.1.2.2.3 | B25: Ensure nosuid option set on /dev/shm partition | C25: Setting this option on a file system prevents users from introducing privileged programs onto the system and allowing non-root users to execute them | D25: -
A26: 1.1.2.2.4 | B26: Ensure noexec option set on /dev/shm partition | C26: Setting this option on a file system prevents users from executing programs from shared memory. This deters users from introducing potentially malicious software on the system | D26: -
A27: Configure /home
A28: 1.1.2.3.1 | B28: Ensure separate partition exists for /home | C28: As /home contains user data, care should be taken to ensure the security and integrity of the data and mount point | D28: -
A29: 1.1.2.3.2 | B29: Ensure nodev option set on /home partition | C29: Since the /home filesystem is not intended to support devices, set this option to ensure that users cannot create a block or character special devices in /home | D29: -
A30: 1.1.2.3.3 | B30: Ensure nosuid option set on /home partition | C30: Since the /home filesystem is only intended for user file storage, set this option to ensure that users cannot create setuid files in /home | D30: -
A31: Configure /var
A32: 1.1.2.4.1 | B32: Ensure separate partition exists for /var | C32: Since the /var directory may contain world writable files and directories, there is a risk of resource exhaustion. It will essentially have the whole disk available to fill up and impact the system. In addition, other operations on the system could fill up the disk unrelated to /var and cause unintended behavior across the system as the disk is full | D32: -
A33: 1.1.2.4.2 | B33: Ensure nodev option set on /var partition | C33: Since the /var filesystem is not intended to support devices, set this option to ensure that users cannot create a block or character special devices in /var | D33: -
A34: 1.1.2.4.3 | B34: Ensure nosuid option set on /var partition | C34: Since the /var filesystem is only intended for variable files such as logs, set this option to ensure that users cannot create setuid files in /var | D34: -
A35: Configure /var/tmp
A36: 1.1.2.5.1 | B36: Ensure separate partition exists for /var/tmp | C36: Since the /var/tmp directory is world-writable, there is a risk of resource exhaustion. In addition, other operations on the system could fill up the disk unrelated to /var/tmp and cause potential disruption to daemons as the disk is full | D36: -
A37: 1.1.2.5.2 | B37: Ensure nodev option set on /var/tmp partition | C37: Since the /var/tmp filesystem is not intended to support devices, set this option to ensure that users cannot create a block or character special devices in /var/tmp | D37: -
A38: 1.1.2.5.3 | B38: Ensure nosuid option set on /var/tmp partition | C38: Since the /var/tmp filesystem is only intended for temporary file storage, set this option to ensure that users cannot create setuid files in /var/tmp | D38: -
A39: 1.1.2.5.4 | B39: Ensure noexec option set on /var/tmp partition | C39: Since the /var/tmp filesystem is only intended for temporary file storage, set this option to ensure that users cannot run executable binaries from /var/tmp | D39: -
A40: Configure /var/log
A41: 1.1.2.6.1 | B41: Ensure separate partition exists for /var/log | C41: As /var/log contains log files, care should be taken to ensure the security and integrity of the data and mount point | D41: -
A42: 1.1.2.6.2 | B42: Ensure nodev option set on /var/log partition | C42: Since the /var/log filesystem is not intended to support devices, set this option to ensure that users cannot create a block or character special devices in /var/log | D42: -
A43: 1.1.2.6.3 | B43: Ensure nosuid option set on /var/log partition | C43: Since the /var/log filesystem is only intended for log files, set this option to ensure that users cannot create setuid files in /var/log | D43: -
A44: 1.1.2.6.4 | B44: Ensure noexec option set on /var/log partition | C44: Since the /var/log filesystem is only intended for log files, set this option to ensure that users cannot run executable binaries from /var/log | D44: -
A45: Configure /var/log/audit
A46: 1.1.2.7.1 | B46: Ensure separate partition exists for /var/log/audit | C46: As /var/log/audit contains audit logs, care should be taken to ensure the security and integrity of the data and mount point | D46: -
A47: 1.1.2.7.2 | B47: Ensure nodev option set on /var/log/audit partition | C47: Since the /var/log/audit filesystem is not intended to support devices, set this option to ensure that users cannot create a block or character special devices in /var/log/audit | D47: -
A48: 1.1.2.7.3 | B48: Ensure nosuid option set on /var/log/audit partition | C48: Since the /var/log/audit filesystem is only intended for variable files such as logs, set this option to ensure that users cannot create setuid files in /var/log/audit | D48: -
A49: 1.1.2.7.4 | B49: Ensure noexec option set on /var/log/audit partition | C49: Since the /var/log/audit filesystem is only intended for audit logs, set this option to ensure that users cannot run executable binaries from /var/log/audit | D49: -
A50: Package Management
A51: Configure Package Repositories
A52: 1.2.1.1 | B52: Ensure the source.list and .source files use the Signed-By option | C52: Verifying that updates originate from a trusted and authenticated source helps mitigate the risk of spoofing attacks, which could otherwise lead to the inadvertent installation of malicious or compromised software | D52: -
A53: 1.2.1.2 | B53: Ensure weak dependencies are configured | C53: Unless a system specifically requires the additional capabilities provides by the weak dependencies, it is recommended that the packages are not installed to reduce the potential attack surface | D53: -
A54: 1.2.1.3 | B54: Ensure access to gpg key files are configured | D54: -
A55: 1.2.1.4 | B55: Ensure access to /etc/apt/trusted.gpg.d directory is configured | D55: -
A56: 1.2.1.5 | B56: Ensure access to /etc/apt/auth.conf.d directory is configured | C56: The /etc/apt/auth.conf.d directory contains APT .conf files which should have restricted access because they control how the package manager runs as root and may contain sensitive information | D56: -
A57: 1.2.1.6 | B57: Ensure access to files in the /etc/apt/auth.conf.d/ directory is configured | C57: Access to the .conf files in the /etc/apt/auth.conf.d directory should be restricted to prevent secrets leakage of Login information needed to connect to a proxy or to download data from a repository | D57: -
A58: 1.2.1.7 | B58: Ensure access to /usr/share/keyrings directory is configured | C58: A non-root user should not be able to add or remove keys from this directory. Misconfiguring could allow a non-root user to add repositories containing malicious packages | D58: -
A59: 1.2.1.8 | B59: Ensure access to /etc/apt/sources.list.d directory is configured | C59: /etc/apt/sources.list.d directory contains files with repositories to be used by APT. A non-root user should not be able to add or remove files from this directory. Misconfiguring could allow a non-root user to add repositories containing malicious packages | D59: -
A60: 1.2.1.9 | B60: Ensure access to files in /etc/apt/sources.list.d are configured | C60: Files in the /etc/apt/sources.list.d directory contain information about repositories to be used by APT. A non-root user should not be able to add or remove files from this directory. Misconfiguring could allow a non-root user to add repositories containing malicious packages | D60: -
A61: Configure Package Updates
A62: 1.2.2.1 | B62: Ensure updates, patches, and additional security software are installed | C62: Periodically patches are released for included software either due to security flaws or to include additional functionality | D62: Nodes-1-3; Nodes-1-5; Nodes-2-2; Nodes-2-6; Nodes-3-5
A63: Mandatory Access Control
A64: Configure AppArmor
A65: 1.3.1.1 | B65: Ensure apparmor packages are installed | C65: Without a Mandatory Access Control system installed only the default Discretionary Access Control system will be available | D65: -
A66: 1.3.1.2 | B66: Ensure AppArmor is enabled | C66: AppArmor is a security mechanism and disabling it is not recommended | D66: -
A67: 1.3.1.3 | B67: Ensure all AppArmor Profiles are enforcing | C67: Security configuration requirements vary from site to site. Some sites may mandate a policy that is stricter than the default policy, which is perfectly acceptable. This item is intended to ensure that any policies that exist on the system are activated | D67: -
A68: 1.3.1.4 | B68: Ensure apparmor_restrict_unprivileged_unconfined is enabled | C68: By making sure the kernel.apparmor_restrict_unprivileged_unconfined sysctl setting is enabled, a process that is unprivileged and unconfined cannot leverage aa-exec to change to a more favourable profile | D68: -
A69: Configure Bootloader
A70: 1.4.1 | B70: Ensure bootloader password is set | C70: Requiring a boot password upon execution of the boot loader will prevent an unauthorized user from entering boot parameters or changing the boot partition | D70: -
A71: 1.4.2 | B71: Ensure access to bootloader config is configured | C71: Setting the permissions to read and write for root only prevents non-root users from seeing the boot parameters or changing them | D71: -
A72: Configure Additional Process Hardening
A73: 1.5.1 | B73: Ensure fs.protected_hardlinks is configured | C73: Disallowing hardlinks mitigates vulnerabilities based on unsecure file systems accessed by privileged programs. This reduces the risk of an exploitation vector exploiting unsafe use of open or creat | D73: -
A74: 1.5.2 | B74: Ensure fs.protected_symlinks is configured | C74: Disallowing symlinks mitigates vulnerabilities based on unsecure file systems accessed by privileged programs. This reduces the risk of an exploitation vector exploiting unsafe use of open or creat | D74: -
A75: 1.5.3 | B75: Ensure kernel.yama.ptrace_scope is configured | C75: Enabling restricted mode will limit the ability of a compromised process to PTRACE_ATTACH on other processes running under the same user. With restricted mode, ptrace will continue to work with root user | D75: -
A76: 1.5.4 | B76: Ensure fs.suid_dumpable is configured | C76: Core dumps may contain sensitive in-memory data like password hashes or keys. An attacker could potentially exploit this to gain access to such data | D76: -
A77: 1.5.5 | B77: Ensure kernel.dmesg_restrict is configured | C77: Restricting access to the kernel message buffer limits access to only root. This prevents attackers from gaining additional system information as a non-privileged user | D77: -
A78: 1.5.6 | B78: Ensure prelink is not installed | C78: The prelinking feature can interfere with the operation of AIDE, because it changes binaries. Prelinking can also increase the vulnerability of the system if a malicious user is able to compromise a common library such as libc | D78: -
A79: 1.5.7 | B79: Ensure Automatic Error Reporting is configured | C79: Apport collects potentially sensitive data, such as core dumps, stack traces, and log files. They can contain passwords, credit card numbers, serial numbers, and other private material | D79: -
A80: 1.5.8 | B80: Ensure kernel.kptr_restrict is configured | C80: Masking the kernel symbols in /proc/kallsyms reduces the ability of an attacker using them to learn more about what to attack on your system | D80: -
A81: 1.5.9 | B81: Ensure kernel.randomize_va_space is configured | C81: Randomly placing virtual memory regions will make it difficult to write memory page exploits as the memory placement will be consistently shifting | D81: -
A82: 1.5.10 | B82: Ensure kernel.yama.ptrace_scope is configured | C82: Enabling restricted mode will limit the ability of a compromised process to PTRACE_ATTACH on other processes running under the same user. With restricted mode, ptrace will continue to work with root user | D82: - | E82: Повтор пункта 1.5.3
A83: 1.5.11 | B83: Ensure core file size is configured | C83: Setting a hard limit on core dumps prevents users from overriding the soft variable. A core dump includes a memory image taken at the time the operating system terminates an application. The memory image could contain sensitive data and is generally useful only for developers trying to debug problems | D83: -
A84: 1.5.12 | B84: Ensure systemd-coredump ProcessSizeMax is configured | C84: A core dump includes a memory image taken at the time the operating system terminates an application. The memory image could contain sensitive data and is generally useful only for developers trying to debug problems, increasing the risk to the system | D84: -
A85: 1.5.13 | B85: Ensure systemd-coredump Storage is configured | C85: A core dump includes a memory image taken at the time the operating system terminates an application. The memory image could contain sensitive data and is generally useful only for developers trying to debug problems | D85: -
A86: Configure Command Line Warning Banners
A87: 1.6.1 | B87: Ensure /etc/motd is configured | C87: Warning messages inform users who are attempting to login to the system of their legal status regarding the system and must include the name of the organization that owns the system and any monitoring policies that are in place. Displaying OS and patch level information in login banners also has the side effect of providing detailed system information to attackers attempting to target specific exploits of a system | D87: -
A88: 1.6.2 | B88: Ensure /etc/issue is configured | C88: Warning messages inform users who are attempting to login to the system of their legal status regarding the system and must include the name of the organization that owns the system and any monitoring policies that are in place. Displaying OS and patch level information in login banners also has the side effect of providing detailed system information to attackers attempting to target specific exploits of a system | D88: -
A89: 1.6.3 | B89: Ensure /etc/issue.net is configured | C89: Warning messages inform users who are attempting to login to the system of their legal status regarding the system and must include the name of the organization that owns the system and any monitoring policies that are in place. Displaying OS and patch level information in login banners also has the side effect of providing detailed system information to attackers attempting to target specific exploits of a system | D89: -
A90: 1.6.4 | B90: Ensure access to /etc/motd is configured | C90: - IF - the /etc/motd file does not have the correct access configured, it could be modified by unauthorized users with incorrect or misleading information | D90: -
A91: 1.6.5 | B91: Ensure access to /etc/issue is configured | C91: - IF - the /etc/issue file does not have the correct access configured, it could be modified by unauthorized users with incorrect or misleading information | D91: -
A92: 1.6.6 | B92: Ensure access to /etc/issue.net is configured | C92: - IF - the /etc/issue.net file does not have the correct access configured, it could be modified by unauthorized users with incorrect or misleading information | D92: -
A93: Configure GNOME Display Manager
A94: 1.7.1 | B94: Ensure GDM is removed | C94: If a Graphical User Interface (GUI) is not required, it should be removed to reduce the attack surface of the system | D94: -
A95: 1.7.2 | B95: Ensure GDM login banner is configured | C95: Warning messages inform users who are attempting to login to the system of their legal status regarding the system and must include the name of the organization that owns the system and any monitoring policies that are in place | D95: -
A96: 1.7.3 | B96: Ensure GDM disable-user-list option is enabled | C96: Displaying the user list eliminates half of the Userid/Password equation that an unauthorized person would need to log on | D96: -
A97: 1.7.4 | B97: Ensure GDM screen locks when the user is idle | C97: Setting a lock-out value reduces the window of opportunity for unauthorized user access to another user's session that has been left unattended | D97: -
A98: 1.7.5 | B98: Ensure GDM screen locks cannot be overridden | C98: Setting a lock-out value reduces the window of opportunity for unauthorized user access to another user's session that has been left unattended. Without locking down the system settings, user settings take precedence over the system settings | D98: -
A99: 1.7.6 | B99: Ensure GDM automatic mounting of removable media is disabled | C99: With automounting enabled anyone with physical access could attach a USB drive or disc and have its contents available in system even if they lacked permissions to mount it themselves | D99: -
A100: 1.7.7 | B100: Ensure GDM disabling automatic mounting of removable media is not overridden | C100: With automounting enabled anyone with physical access could attach a USB drive or disc and have its contents available in system even if they lacked permissions to mount it themselves | D100: -
...

Sheet CIS Linux (RHEL)
A1: ID в CIS k8s | B1: Требование | C1: Примечание | D1: JCSF
A2: Initial Setup
A3: Filesystem
A4: Configure Filesystem Kernel Modules
A5: 1.1.1.1 | B5: Ensure cramfs kernel module is not available | C5: Removing support for unneeded filesystem types reduces the local attack surface of the system. If this filesystem type is not needed, disable it | D5: -
A6: 1.1.1.2 | B6: Ensure freevxfs kernel module is not available | C6: Removing support for unneeded filesystem types reduces the local attack surface of the system. If this filesystem type is not needed, disable it | D6: -
A7: 1.1.1.3 | B7: Ensure hfs kernel module is not available | C7: Removing support for unneeded filesystem types reduces the local attack surface of the system. If this filesystem type is not needed, disable it | D7: -
A8: 1.1.1.4 | B8: Ensure hfsplus kernel module is not available | C8: Removing support for unneeded filesystem types reduces the local attack surface of the system. If this filesystem type is not needed, disable it | D8: -
A9: 1.1.1.5 | B9: Ensure jffs2 kernel module is not available | C9: Removing support for unneeded filesystem types reduces the local attack surface of the system. If this filesystem type is not needed, disable it | D9: -
A10: 1.1.1.6 | B10: Ensure overlay kernel module is not available | C10: Disabling the overlay kernel module reduces the local attack surface by removing support for unnecessary filesystem types and mitigates potential risks associated with unauthorized execution of setuid files, enhancing the overall system security | D10: -
A11: 1.1.1.7 | B11: Ensure squashfs kernel module is not available | C11: Removing support for unneeded filesystem types reduces the local attack surface of the system. If this filesystem type is not needed, disable it | D11: -
A12: 1.1.1.8 | B12: Ensure udf kernel module is not available | C12: Removing support for unneeded filesystem types reduces the local attack surface of the system. If this filesystem type is not needed, disable it | D12: -
A13: 1.1.1.9 | B13: Ensure firewire-core kernel module is not available | C13: Disabling FireWire protects the system against exploitation of any flaws in its implementation | D13: -
A14: 1.1.1.10 | B14: Ensure usb-storage kernel module is not available | C14: Restricting USB access on the system will decrease the physical attack surface for a device and diminish the possible vectors to introduce malware | D14: -
A15: 1.1.1.11 | B15: Ensure unused filesystems kernel modules are not available | C15: Removing support for unneeded filesystem types reduces the local attack surface of the system. If this filesystem type is not needed, disable it | D15: -
A16: Configure Filesystem Partitions
A17: Configure /tmp
A18: 1.1.2.1.1 | B18: Ensure /tmp is tmpfs or a separate partition | C18: Making /tmp its own file system allows an administrator to set additional mount options such as the noexec option on the mount, making /tmp useless for an attacker to install executable code. It would also prevent an attacker from establishing a hard link to a system setuid program and wait for it to be updated. Once the program was updated, the hard link would be broken, and the attacker would have his own copy of the program | D18: -
A19: 1.1.2.1.2 | B19: Ensure nodev option set on /tmp partition | C19: Since the /tmp filesystem is not intended to support devices, set this option to ensure that users cannot create a block or character special devices in /tmp | D19: -
A20: 1.1.2.1.3 | B20: Ensure nosuid option set on /tmp partition | C20: Since the /tmp filesystem is only intended for temporary file storage, set this option to ensure that users cannot create setuid files in /tmp | D20: -
A21: 1.1.2.1.4 | B21: Ensure noexec option set on /tmp partition | C21: Since the /tmp filesystem is only intended for temporary file storage, set this option to ensure that users cannot run executable binaries from /tmp | D21: -
A22: Configure /dev/shm
A23: 1.1.2.2.1 | B23: Ensure /dev/shm is tmpfs or a separate partition | C23: Making /dev/shm its own file system allows an administrator to set additional mount options such as the noexec option on the mount, making /dev/shm useless for an attacker to install executable code. It would also prevent an attacker from establishing a hard link to a system setuid program and wait for it to be updated. Once the program was updated, the hard link would be broken and the attacker would have his own copy of the program | D23: -
A24: 1.1.2.2.2 | B24: Ensure nodev option set on /dev/shm partition | C24: Since the /dev/shm filesystem is not intended to support devices, set this option to ensure that users cannot attempt to create special devices in /dev/shm partitions | D24: -
A25: 1.1.2.2.3 | B25: Ensure nosuid option set on /dev/shm partition | C25: Setting this option on a file system prevents users from introducing privileged programs onto the system and allowing non-root users to execute them | D25: -
A26: 1.1.2.2.4 | B26: Ensure noexec option set on /dev/shm partition | C26: Setting this option on a file system prevents users from executing programs from shared memory. This deters users from introducing potentially malicious software on the system | D26: -
A27: Configure /home
A28: 1.1.2.3.1 | B28: Ensure separate partition exists for /home | C28: As /home contains user data, care should be taken to ensure the security and integrity of the data and mount point | D28: -
A29: 1.1.2.3.2 | B29: Ensure nodev option set on /home partition | C29: Since the /home filesystem is not intended to support devices, set this option to ensure that users cannot create a block or character special devices in /home | D29: -
A30: 1.1.2.3.3 | B30: Ensure nosuid option set on /home partition | C30: Since the /home filesystem is only intended for user file storage, set this option to ensure that users cannot create setuid files in /home | D30: -
A31: Configure /var
A32: 1.1.2.4.1 | B32: Ensure separate partition exists for /var | C32: Since the /var directory may contain world writable files and directories, there is a risk of resource exhaustion. It will essentially have the whole disk available to fill up and impact the system. In addition, other operations on the system could fill up the disk unrelated to /var and cause unintended behavior across the system as the disk is full | D32: -
A33: 1.1.2.4.2 | B33: Ensure nodev option set on /var partition | C33: Since the /var filesystem is not intended to support devices, set this option to ensure that users cannot create a block or character special devices in /var | D33: -
A34: 1.1.2.4.3 | B34: Ensure nosuid option set on /var partition | C34: Since the /var filesystem is only intended for variable files such as logs, set this option to ensure that users cannot create setuid files in /var | D34: -
A35: Configure /var/tmp
A36: 1.1.2.5.1 | B36: Ensure separate partition exists for /var/tmp | C36: Since the /var/tmp directory is world-writable, there is a risk of resource exhaustion. In addition, other operations on the system could fill up the disk unrelated to /var/tmp and cause potential disruption to daemons as the disk is full | D36: -
A37: 1.1.2.5.2 | B37: Ensure nodev option set on /var/tmp partition | C37: Since the /var/tmp filesystem is not intended to support devices, set this option to ensure that users cannot create a block or character special devices in /var/tmp | D37: -
A38: 1.1.2.5.3 | B38: Ensure nosuid option set on /var/tmp partition | C38: Since the /var/tmp filesystem is only intended for temporary file storage, set this option to ensure that users cannot create setuid files in /var/tmp | D38: -
A39: 1.1.2.5.4 | B39: Ensure noexec option set on /var/tmp partition | C39: Since the /var/tmp filesystem is only intended for temporary file storage, set this option to ensure that users cannot run executable binaries from /var/tmp | D39: -
A40: Configure /var/log
A41: 1.1.2.6.1 | B41: Ensure separate partition exists for /var/log | C41: As /var/log contains log files, care should be taken to ensure the security and integrity of the data and mount point | D41: -
A42: 1.1.2.6.2 | B42: Ensure nodev option set on /var/log partition | C42: Since the /var/log filesystem is not intended to support devices, set this option to ensure that users cannot create a block or character special devices in /var/log | D42: -
A43: 1.1.2.6.3 | B43: Ensure nosuid option set on /var/log partition | C43: Since the /var/log filesystem is only intended for log files, set this option to ensure that users cannot create setuid files in /var/log | D43: -
A44: 1.1.2.6.4 | B44: Ensure noexec option set on /var/log partition | C44: Since the /var/log filesystem is only intended for log files, set this option to ensure that users cannot run executable binaries from /var/log | D44: -
A45: Configure /var/log/audit
A46: 1.1.2.7.1 | B46: Ensure separate partition exists for /var/log/audit | C46: As /var/log/audit contains audit logs, care should be taken to ensure the security and integrity of the data and mount point | D46: -
A47: 1.1.2.7.2 | B47: Ensure nodev option set on /var/log/audit partition | C47: Since the /var/log/audit filesystem is not intended to support devices, set this option to ensure that users cannot create a block or character special devices in /var/log/audit | D47: -
A48: 1.1.2.7.3 | B48: Ensure nosuid option set on /var/log/audit partition | C48: Since the /var/log/audit filesystem is only intended for variable files such as logs, set this option to ensure that users cannot create setuid files in /var/log/audit | D48: -
A49: 1.1.2.7.4 | B49: Ensure noexec option set on /var/log/audit partition | C49: Since the /var/log/audit filesystem is only intended for audit logs, set this option to ensure that users cannot run executable binaries from /var/log/audit | D49: -
A50: Package Management
A51: Configure Package Repositories
A52: 1.2.1.1 | B52: Ensure GPG keys are configured | C52: It is important to ensure that updates are obtained from a valid source to protect against spoofing that could lead to the inadvertent installation of malware on the system. To this end, verify that GPG keys are configured correctly for your system | D52: -
A53: 1.2.1.2 | B53: Ensure gpgcheck is configured | C53: It is important to ensure that an RPM's package signature is always checked prior to installation to ensure that the software is obtained from a trusted source | D53: -
A54: 1.2.1.3 | B54: Ensure repo_gpgcheck is globally activated | C54: It is important to ensure that the repository data signature is always checked prior to installation to ensure that the software is not tampered with in any way | D54: -
A55: 1.2.1.4 | B55: Ensure package manager repositories are configured | C55: If a system's package repositories are misconfigured, important patches may not be identified or a rogue repository could introduce compromised software | D55: -
A56: 1.2.1.5 | B56: Ensure weak dependencies are configured | C56: Unless a system specifically requires the additional capabilities provides by the weak dependencies, it is recommended that the packages are not installed to reduce the potential attack surface | D56: -
A57: Configure Package Updates
A58: 1.2.2.1 | B58: Ensure updates, patches, and additional security software are installed | D58: Nodes-1-3; Nodes-1-5; Nodes-2-2; Nodes-2-6; Nodes-3-5
A59: Mandatory Access Control
A60: Configure SELinux
A61: 1.3.1.1 | B61: Ensure SELinux is installed | C61: Without a Mandatory Access Control system installed only the default Discretionary Access Control system will be available | D61: -
A62: 1.3.1.2 | B62: Ensure SELinux is not disabled in bootloader configuration | C62: SELinux must be enabled at boot time in your grub configuration to ensure that the controls it provides are not overridden | D62: -
A63: 1.3.1.3 | B63: Ensure SELinux policy is configured | C63: Security configuration requirements vary from site to site. Some sites may mandate a policy that is stricter than the default policy, which is perfectly acceptable. This item is intended to ensure that at least the default recommendations are met | D63: -
A64: 1.3.1.4 | B64: Ensure the SELinux mode is not disabled | C64: Running SELinux in disabled mode is strongly discouraged; not only does the system avoid enforcing the SELinux policy, it also avoids labeling any persistent objects such as files, making it difficult to enable SELinux in the future | D64: -
A65: 1.3.1.5 | B65: Ensure the SELinux mode is enforcing | C65: Running SELinux in disabled mode is strongly discouraged; not only does the system avoid enforcing the SELinux policy, it also avoids labeling any persistent objects such as files, making it difficult to enable SELinux in the future. Running SELinux in Permissive mode, though helpful for developing SELinux policy, only logs access denial entries, but does not deny any operations | D65: -
A66: 1.3.1.6 | B66: Ensure no unconfined services exist | C66: For unconfined processes, SELinux policy rules are applied, but policy rules exist that allow processes running in unconfined domains almost all access. Processes running in unconfined domains fall back to using DAC rules exclusively. If an unconfined process is compromised, SELinux does not prevent an attacker from gaining access to system resources and data, but of course, DAC rules are still used. SELinux is a security enhancement on top of DAC rules – it does not replace them | D66: -
A67: 1.3.1.7 | B67: Ensure the MCS Translation Service (mcstrans) is not installed | C67: Since this service is not used very often, remove it to reduce the amount of potentially vulnerable code running on the system | D67: -
A68: 1.3.1.8 | B68: Ensure SETroubleshoot is not installed | C68: The SETroubleshoot service is an unnecessary daemon to have running on a server, especially if X Windows is disabled | D68: -
A69: Configure Bootloader
A70: 1.4.1 | B70: Ensure bootloader password is set | C70: Requiring a boot password upon execution of the boot loader will prevent an unauthorized user from entering boot parameters or changing the boot partition | D70: -
A71: 1.4.2 | B71: Ensure access to bootloader config is configured | C71: Setting the permissions to read and write for root only prevents non-root users from seeing the boot parameters or changing them | D71: -
A72: Configure Additional Process Hardening
A73: 1.5.1 | B73: Ensure core file size is configured | C73: Setting a hard limit on core dumps prevents users from overriding the soft variable. A core dump includes a memory image taken at the time the operating system terminates an application. The memory image could contain sensitive data and is generally useful only for developers trying to debug problems | D73: -
A74: 1.5.2 | B74: Ensure fs.protected_hardlinks is configured | C74: Disallowing hardlinks mitigates vulnerabilities based on unsecure file systems accessed by privileged programs. This reduces the risk of an exploitation vector exploiting unsafe use of open or creat | D74: -
A75: 1.5.3 | B75: Ensure fs.protected_symlinks is configured | C75: Disallowing symlinks mitigates vulnerabilities based on unsecure file systems accessed by privileged programs. This reduces the risk of an exploitation vector exploiting unsafe use of open or creat | D75: -
A76: 1.5.4 | B76: Ensure fs.suid_dumpable is configured | C76: Core dumps may contain sensitive in-memory data like password hashes or keys. An attacker could potentially exploit this to gain access to such data | D76: -
A77: 1.5.5 | B77: Ensure kernel.dmesg_restrict is configured | C77: Restricting access to the kernel message buffer limits access to only root. This prevents attackers from gaining additional system information as a non-privileged user | D77: -
A78: 1.5.6 | B78: Ensure kernel.kptr_restrict is configured | C78: Masking the kernel symbols in /proc/kallsyms reduces the ability of an attacker using them to learn more about what to attack on your system | D78: -
A79: 1.5.7 | B79: Ensure kernel.yama.ptrace_scope is configured | C79: Enabling restricted mode will limit the ability of a compromised process to PTRACE_ATTACH on other processes running under the same user. With restricted mode, ptrace will continue to work with root user | D79: -
A80: 1.5.8 | B80: Ensure kernel.randomize_va_space is configured | C80: Randomly placing virtual memory regions will make it difficult to write memory page exploits as the memory placement will be consistently shifting | D80: -
A81: 1.5.9 | B81: Ensure systemd-coredump ProcessSizeMax is configured | C81: A core dump includes a memory image taken at the time the operating system terminates an application. The memory image could contain sensitive data and is generally useful only for developers trying to debug problems, increasing the risk to the system | D81: -
A82: 1.5.10 | B82: Ensure systemd-coredump Storage is configured | C82: A core dump includes a memory image taken at the time the operating system terminates an application. The memory image could contain sensitive data and is generally useful only for developers trying to debug problems | D82: -
A83: Configure system wide crypto policy
A84: 1.6.1 | B84: Ensure system wide crypto policy is not set to legacy | C84: The LEGACY system-wide crypto policy includes support for outdated and weakened algorithms to ensure maximum compatibility with Red Hat Enterprise Linux 6 and earlier; it is less secure due to an increased attack surface. These legacy protocols and algorithms can make the system vulnerable to attacks, including those listed in RFC 7457 | D84: -
A85: 1.6.2 | B85: Ensure system wide crypto policy disables sha1 hash and signature support | C85: The SHA-1 hash function has an inherently weak design, and advancing cryptanalysis has made it vulnerable to attacks. The most significant danger for a hash algorithm is when a "collision" which happens when two different pieces of data produce the same hash value occurs. This hashing algorithm has been considered weak since 2005 | D85: -
A86: 1.6.3 | B86: Ensure system wide crypto policy macs are configured | C86: A MAC algorithm must be computationally infeasible to determine the MAC of a message without knowledge of the key, even if one has already seen the results of using that key to compute the MAC's of other messages | D86: -
A87: 1.6.4 | B87: Ensure system wide crypto policy disables cbc for ssh | C87: A vulnerability exists in SSH messages that employ CBC mode that may allow an attacker to recover plaintext from a block of ciphertext | D87: -
A88: Configure Command Line Warning Banners
A89: 1.7.1 | B89: Ensure /etc/motd is configured | C89: Warning messages inform users who are attempting to login to the system of their legal status regarding the system and must include the name of the organization that owns the system and any monitoring policies that are in place. Displaying OS and patch level information in login banners also has the side effect of providing detailed system information to attackers attempting to target specific exploits of a system | D89: -
A90: 1.7.2 | B90: Ensure /etc/issue is configured | C90: Warning messages inform users who are attempting to login to the system of their legal status regarding the system and must include the name of the organization that owns the system and any monitoring policies that are in place. Displaying OS and patch level information in login banners also has the side effect of providing detailed system information to attackers attempting to target specific exploits of a system | D90: -
A91: 1.7.3 | B91: Ensure /etc/issue.net is configured | C91: Warning messages inform users who are attempting to login to the system of their legal status regarding the system and must include the name of the organization that owns the system and any monitoring policies that are in place. Displaying OS and patch level information in login banners also has the side effect of providing detailed system information to attackers attempting to target specific exploits of a system | D91: -
A92: 1.7.4 | B92: Ensure access to /etc/motd is configured | C92: - IF - the /etc/motd file does not have the correct access configured, it could be modified by unauthorized users with incorrect or misleading information | D92: -
A93: 1.7.5 | B93: Ensure access to /etc/issue is configured | C93: - IF - the /etc/issue file does not have the correct access configured, it could be modified by unauthorized users with incorrect or misleading information | D93: -
A94: 1.7.6 | B94: Ensure access to /etc/issue.net is configured | C94: - IF - the /etc/issue.net file does not have the correct access configured, it could be modified by unauthorized users with incorrect or misleading information | D94: -
A95: Configure GNOME Display Manager
A96: 1.8.1 | B96: Ensure GDM login banner is configured | C96: Warning messages inform users who are attempting to login to the system of their legal status regarding the system and must include the name of the organization that owns the system and any monitoring policies that are in place | D96: -
A97: 1.8.2 | B97: Ensure GDM disable-user-list option is configured | C97: Displaying the user list eliminates half of the Userid/Password equation that an unauthorized person would need to log on | D97: -
A98: 1.8.3 | B98: Ensure GDM screen lock is configured | C98: Setting a lock-out value reduces the window of opportunity for unauthorized user access to another user's session that has been left unattended. Without locking down the system settings, user settings take precedence over the system settings | D98: -
A99: 1.8.4 | B99: Ensure GDM automount is configured | C99: With automounting enabled anyone with physical access could attach a USB drive or disc and have its contents available in system even if they lacked permissions to mount it themselves | D99: -
A100: 1.8.5 | B100: Ensure GDM autorun-never is configured | C100: Malware on removable media may taking advantage of Autorun features when the media is inserted into a system and execute | D100: -
...

Sheet Приказ 118
A1: № пункта Приказа | B1: Описание | D1: Требование | E1: JCSF ID | F1: JCSF Требование | G1: Комментарий
A2: 9 | B2: К изоляции контейнеров средством контейнеризации предъявляются следующие требования | C2: 9.1 | D2: Средство контейнеризации 6 класса защиты должно реализовывать механизмы изоляции контейнеров. Способы реализации изоляции контейнеров устанавливаются разработчиком средства контейнеризации. | E2: CONT-1-1 | F2: Используются профили по умолчанию Secomp
E3: CONT-3-5 | F3: Ограничиваются вычислительные ресурсы работающего контейнера
E4: Dock-1-6 | F4: Определена единая cgroup (control group) по умолчанию для всех контейнеров
E5: Dock-4-5 | F5: Определены отдельные cgroup (control group) для групп контейнеров
C6: 9.2 | D6: Средство контейнеризации 5 и 4 классов защиты наряду с требованиями, установленными подпунктом 9.1 пункта 9 настоящих Требований, дополнительно должно реализовывать следующие механизмы: - изоляция пространств идентификаторов процессов контейнеров; - изоляция пространств имен для межпроцессного взаимодействия - контейнеров; - изоляция пространств имен для пользователей и групп контейнеров; - изоляция пространств имен хостов и доменов контейнеров; - изоляция сетевых пространств имен контейнеров; - изоляция пространств имен для иерархии каталогов контейнеров. | E6: MAN-1-3 | F6: В конфигурациях для контейнеров не используется host network (сеть хоста)
E7: MAN-2-5 | F7: В манифестах не используются пространтсва имен PID, разделенные между хост-сервером и контейнером
E8: MAN-2-6 | F8: В манифестах не используются пространтсва имен IPC разделенные между хост-сервером и контейнером
E9: MAN-2-7 | F9: В манифестах не используются пространтсва имен разделенные UTS между хост-сервером и контейнером
A10: 10 | B10: К выявлению уязвимостей в образах контейнеров предъявляются следующие требования: | C10: 10.1 | D10: Средство контейнеризации 6 класса защиты должно: - выявлять известные уязвимости при создании, установке образа контейнера в информационной (автоматизированной) системе и хранении образов контейнеров во взаимодействии с сертифицированным средством контроля и анализа защищенности на основе сведений, содержащихся в банке данных угроз безопасности информации, ведение которого осуществляется ФСТЭК России в соответствии с подпунктом 21 пункта 8 Положения о Федеральной службе по техническому и экспортному контролю, утвержденного Указом Президента Российской Федерации от 16 августа 2004 г.№ 1085 (Собрание законодательства Российской Федерации, 2004, № 34, ст.3541), а также в иных источниках, содержащих сведения об известных уязвимостях; - оповещать о выявленных уязвимостях в образах контейнеров разработчика образов контейнеров и администратора безопасности информационной (автоматизированной) системы. Средство контейнеризации 6 класса защиты должно осуществлять выявление известных уязвимостей образов контейнеров не реже одного раза в месяц. | E10: IMG-2-1 | F10: Образы контейнеров не должны содержать уязвимостей, которые возможно проэксплуатировать
E11: IMG-2-2 | F11: Выполняется сканирование образов контейнеров в CI/CD на наличие уязвимостей
E12: IMG-3-2 | F12: На образы регулярно устанавливаются обновления (обновляются базовые образы)
E13: CONT-3-6 | F13: Используется мониторинг аномалий для запущенных контейнеров
C14: 10.2 | D14: Средство контейнеризации 5 и 4 классов защиты наряду с требованиями, установленными подпунктом 10.1 пункта 10 настоящих Требований, должно запрещать создание образов контейнеров, содержащих известные уязвимости критического и высокого уровня опасности. Средство контейнеризации 5 и 4 классов защиты должно осуществлять выявление известных уязвимостей образов контейнеров не реже одного раза в неделю. | E14: IMG-3-4 | F14: Выполняется периодическое сканирование образов контейнеров, размещенных во внутренних репозиториях, на наличие уязвимостей
E15: IMG-4-2 | F15: Сборки в CI/CD блокируются при найденных уязвимостях в образах контейнеров по договоренности между ИБ и разработчиками
A16: 11 | B16: К проверке корректности конфигурации контейнеров в средстве контейнеризации предъявляются следующие требования: | C16: 11 | D16: Средство контейнеризации 6, 5 и 4 классов защиты должно обеспечивать: - ограничение прав прикладного программного обеспечения, - выполняемого внутри контейнера, на использование периферийных устройств, устройств хранения данных и съемных машинных носителей информации (блочных устройств), входящих в состав информационной (автоматизированной) системы; - ограничение прав прикладного программного обеспечения, выполняемого внутри контейнера, на использование вычислительных ресурсов (оперативной памяти, операций ввода-вывода за период времени) хостовой операционной системы; - монтирование корневой файловой системы хостовой операционной системы в режиме «только для чтения». | E16: MAN-1-2 | F16: В манифестах не используется флаг privileged для контейнеров
E17: MAN-2-8 | F17: В манифестах настроены ограничения для контейнеров (limits и requests, ulimits или другая опция)
E18: MAN-3-3 | F18: В конфигурациях deployments/replicasets/pods/daemonsets/statefulsets для контейнеров, используется read only корневая системы (readOnlyRootFilesystem)
E19: MAN-3-4 | F19: Настроены политики средства контроля запускаемых сущностей, требующих в конфигурации указывать необходимые capabilities
E20: MAN-4-1 | F20: Для групп контейнеров используются отдельные apparmor-профайлы
E21: MAN-4-2 | F21: Для групп контейнеров используются отдельные seccomp-профайлы
E22: Dock-2-3 | F22: Настроены лимиты (ulimits) для контейнеров по умолчанию
E23: Dock-2-10 | F23: Используется средство контроля параметров запускаемых контейнеров
E24: CONT-2-3 | F24: Осуществляется мониторинг запускаемых процессов, сетевых соединений и использования файлов в контейнерах. Используются правила по умолчанию
A25: 12 | B25: К контролю целостности контейнеров и их образов в средстве контейнеризации предъявляются следующие требования: | C25: 12.1 | D25: Средство контейнеризации 6 класса защиты должно: - контролировать самостоятельно или с применением средств контроля целостности хостовой операционной системы и иных сертифицированных средств защиты информации целостность образов контейнеров и исполняемых файлов контейнеров; - информировать администратора информационной (автоматизированной) системы и администратора безопасности средства контейнеризации о нарушении целостности объектов контроля. | E25: IMG-3-3 | F25: Собираемые образы подписываются электронной подписью при сборке, а также осуществляется их проверка
C26: 12.2 | D26: Средство контейнеризации 5 класса защиты наряду с требованиями, установленными подпунктом 12.1 пункта 12 настоящих Требований, должно контролировать целостность параметров настройки средства контейнеризации. | E26: Dock-2-2 | F26: Настроен аудит для ключевых файлов, относящихся к демону Docker | G26: Нет контроля целостности для конфигурационных файлов k8S
E27: Dock-3-3 | F27: Контролируется целостность исполняемых файлов Docker, а также его конфигураций
C28: 12.3 | D28: Средство контейнеризации 4 класса защиты наряду с требованиями, установленными подпунктами 12.1 и 12.2 пункта 12 настоящих Требований, должно: - контролировать целостность сведений о событиях безопасности самостоятельно или во взаимодействии с хостовой операционной системой и иными сертифицированными средствами защиты информации; - контролировать целостность образов контейнеров и параметров настройки средства контейнеризации при установке образа контейнера в информационной (автоматизированной) системе и далее периодически за счет применения цифровой подписи самостоятельно или во взаимодействии с хостовой операционной системой и иными сертифицированными средствами защиты информации; - блокировать запуск образа контейнера при нарушении его целостности. | E28: Orch-2-8 | F28: Настроены параметры аудита сред оркестрации (k8s audit policy), логи передаются и анализируются в SIEM
A29: 13 | B29: К регистрации событий безопасности в средстве контейнеризации предъявляются следующие требования: | C29: 13.1 | D29: Средство контейнеризации 6 класса защиты должно: - регистрировать события, относящиеся к инцидентам безопасности средства контейнеризации, связанные с попытками осуществления несанкционированного доступа к средству контейнеризации; - оповещать администратора безопасности средства контейнеризации и администратора информационной (автоматизированной) системы об инцидентах безопасности; - выполнять действия, являющиеся реакцией на инциденты безопасности; - осуществлять сбор и хранение записей в журнале событий безопасности, которые позволяют определить, когда и какие действия происходили. Регистрация событий безопасности в средстве контейнеризации должна осуществляться с учетом требований разделов 5-6 ГОСТ Р 59548-2022 «Защита информации. Регистрация событий безопасности. Требования к регистрируемой информации». Для каждой функции безопасности в средстве контейнеризации должен быть определен перечень событий, необходимых для регистрации и учета. Для регистрируемых событий безопасности в каждой записи журнала событий безопасности должны указываться номер (уникальный идентификатор) события, дата, время, тип события безопасности. Записи журнала событий безопасности должны представляться в структурированном виде и содержать информацию о времени события безопасности, взятую из хостовой операционной системы. Средство контейнеризации должно осуществлять запись событий безопасности контейнеров в журнал событий безопасности информационной (автоматизированной) системы с указанием идентификатора контейнера. Журнал событий безопасности средства контейнеризации должен быть доступен только для чтения. При исчерпании области памяти, отведенной под журнал событий безопасности средства контейнеризации, средство контейнеризации должно осуществлять архивирование журнала с последующей очисткой указанного журнала. Регистрации подлежат как минимум следующие события безопасности: -неуспешные попытки аутентификации пользователей средства контейнеризации; - создание, модификация и удаление образов контейнеров; - получение доступа к образам контейнеров; - запуск и остановка контейнеров с указанием причины остановки. - изменение ролевой модели; - модификация запускаемых контейнеров. | E29: Nodes-2-9 | F29: Определены и настроены критичные события, которые должны собираться с *nix-серверов (перечень параметров). События передаются и анализируются в SIEM
E30: Orch-2-8 | F30: Настроены параметры аудита сред оркестрации (k8s audit policy), логи передаются и анализируются в SIEM
C31: 13.2 | D31: Средство контейнеризации 5 класса защиты наряду с требованиями, установленными подпунктом 13.1 пункта 13 настоящих Требований, должно регистрировать следующие события безопасности: - выявление известных уязвимостей в образах контейнеров и некорректности конфигурации; - факты нарушения целостности объектов контроля. Для каждого события безопасности должны регистрироваться: - описание события безопасности; - сведения о критичности события безопасности. | E31: IMG-3-3 | F31: Собираемые образы подписываются электронной подписью при сборке, а также осуществляется их проверка
E32: IMG-3-4 | F32: Выполняется периодическое сканирование образов контейнеров, размещенных во внутренних репозиториях, на наличие уязвимостей
C33: 13.3 | D33: Средство контейнеризации 4 класса защиты наряду с требованиями, установленными подпунктами 13.1 и 13.2 пункта 13 настоящих Требований, должно обеспечивать запись событий безопасности контейнеров в журнал событий безопасности информационной (автоматизированной) системы с указанием идентификатора пользователя хостовой операционной системы, от имени которого был запущен контейнер.
A34: 14 | B34: В средстве контейнеризации 6, 5 и 4 классов защиты должен быть реализован ролевой метод управления доступом с тремя ролями пользователей: разработчик образов контейнеров; администратор безопасности средства контейнеризации; администратор информационной (автоматизированной) системы. | C34: 14.1 | D34: Роль разработчика образов контейнеров должна позволять: -менять установленный администратором безопасности средства контейнеризации для разработчика пароль; - создавать, модифицировать и удалять образы контейнеров.
C35: 14.2 | D35: Роль администратора информационной (автоматизированной) системы должна позволять: - менять установленный администратором безопасности средства контейнеризации для администратора информационной (автоматизированной) системы пароль; - запускать и останавливать контейнеры. | E35: Orch-2-10 | F35: При администрировании оркестратора используется ролевая модель, при назначении прав используется принцип минимальных привилегий
C36: 14.3 | D36: Роль администратора безопасности средства контейнеризации должна позволять: - назначать права доступа пользователям средства контейнеризации к образам контейнеров; - создавать учетные записи пользователей средства контейнеризации; - управлять учетными записями пользователей средства контейнеризации; - иметь доступ на чтение к журналу событий безопасности средства контейнеризации; - формировать отчеты с учетом заданных критериев отбора, выгрузку (экспорт) данных из журнала событий безопасности средства контейнеризации. | E36: Orch-2-10 | F36: При администрировании оркестратора используется ролевая модель, при назначении прав используется принцип минимальных привилегий
A37: 15 | B37: К идентификации и аутентификации пользователей в средстве контейнеризации предъявляются следующие требования: | C37: 15.1 | D37: Первичная идентификация пользователей средства контейнеризации 6 класса защиты должна осуществляться администратором безопасности средства контейнеризации. Идентификация и аутентификация пользователей в средстве контейнеризации осуществляется с учетом требований разделов 4-7 ГОСТ Р 58833-2020 «Защита информации. Идентификация и аутентификация. Общие положения». Средство контейнеризации должно осуществлять аутентификацию пользователей при предъявлении пароля пользователя. Пароль пользователя должен устанавливаться администратором безопасности средства контейнеризации. Средство контейнеризации должно обеспечивать возможность смены установленного администратором безопасности средства контейнеризации пароля пользователя после его первичной аутентификации. При попытке ввода неправильного значения пароля пользователя должно выводиться соответствующее сообщение с приглашением ввести правильный пароль еще раз. При исчерпании установленного максимального количества неуспешных попыток ввода неправильного пароля учетная запись пользователя средства контейнеризации должна быть заблокирована средством контейнеризации с возможностью разблокировки администратором безопасности средства контейнеризации. Защита пароля пользователя должна обеспечиваться при его вводе за счет отображения вводимых символов условными знаками. Пароль пользователя средства контейнеризации 6 класса защиты должен содержать не менее 6 символов при алфавите пароля не менее 60 символов. Максимальное количество неуспешных попыток аутентификации (ввода неправильного пароля) до блокировки – 10. Средство контейнеризации должно обеспечивать хранение аутентификационной информации пользователя средства контейнеризации в защищенном формате или в защищенном хранилище. | E37: Orch-1-1 | F37: Для доступа к kube-apiserver используется аутентификация и авторизация
E38: Orch-2-11 | F38: Для аутентификации в оркестраторе используется внешний сервис, например Active Directory
C39: 15.2 | D39: Пароль пользователя средства контейнеризации 5 класса защиты должен содержать не менее 6 символов при алфавите пароля не менее 70 символов. Максимальное количество неуспешных попыток аутентификации (ввода неправильного пароля) до блокировки – 8.
C40: 15.3 | D40: Средство контейнеризации 4 класса защиты наряду с требованиями, установленными подпунктом 15.1 пункта 15 не должно запускать процессы в хостовой операционной системе, обладающие привилегиями администратора информационной (автоматизированной) системы и администратора безопасности информационной (автоматизированной) системы. Пароль пользователя средства контейнеризации 4 класса защиты должен содержать не менее 8 символов при алфавите пароля не менее 70 символов. Максимальное количество неуспешных попыток аутентификаци (ввода неправильного пароля) до блокировки – 4.
A41: 16 | B41: К централизованному управлению образами контейнеров и контейнерами в средстве контейнеризации предъявляются следующие требования: | C41: 16.1 | D41: Средство контейнеризации 6 класса защиты должно: - создавать, модифицировать, хранить, получать и удалять образы контейнеров в информационной (автоматизированной) системе; - обновлять образы контейнеров; - обеспечивать чтение, удаление записей о событиях безопасности, формирование отчетов с учетом заданных критериев отбора, выгрузку (экспорт) данных из журнала событий безопасности средства контейнеризации.
C42: 16.2 | D42: Средство контейнеризации 5 и 4 классов защиты наряду с требованиями, установленными подпунктом 16.1 пункта 16 настоящих Требований, должно: - анализировать возникающие события безопасности в целях выявления инцидентов безопасности; - оповещать администратора безопасности средства контейнеризации о событиях безопасности; - формировать отчеты | E42: CONT-2-3 | F42: Осуществляется мониторинг запускаемых процессов, сетевых соединений и использования файлов в контейнерах. Используются правила по умолчанию
E43: CONT-3-3 | F43: Осуществляется мониторинг запускаемых процессов, сетевых соединений и использования файлов в контейнерах. Правила регулярно обновляются и учитывают актуальные угрозы
E44: CONT-3-6 | F44: Используется мониторинг аномалий для запущенных контейнеров
E45: MAN-3-2 | F45: Осуществляется контроль за выполнением команд внутри контейнера от пользователя root Настроены политики средства контроля запускаемых сущностей, ограничивающие запуск контейнеров с пользователем root
